sim/shiftsim/shift_16bit.v
module shift_16Bit
	(
		input [15:0] data,
		input clk,
		input en,
		output reg  [15:0] out_0 ,
		output reg  [15:0] out_1 ,
		output reg  [15:0] out_2 ,
		output reg  [15:0] out_3 ,
		output reg  [15:0] out_4 ,
		output reg  [15:0] out_5 ,
		output reg  [15:0] out_6 ,
		output reg  [15:0] out_7 
		);


always @(posedge clk)
begin
	if(en)
	begin
		out_7 <= out_6;
		out_6 <= out_5;
		out_5 <= out_4;
		out_4 <= out_3;
		out_3 <= out_2;
		out_2 <= out_1;
		out_1 <= out_0;
		out_0 <= data;
	end
	else begin
		out_0 <= out_0;
		out_1 <= out_1;
		out_2 <= out_2;
		out_3 <= out_3;
		out_4 <= out_4;
		out_5 <= out_5;
		out_6 <= out_6;
		out_7 <= out_7;
	end
end
endmodule // shift_16Bit

sim/shiftsim/shift_reg_tb.v
`define DUMPSTR(x) `"x.vcd`"
`timescale 100 ns / 10 ns

module tb_shift;

parameter MSB = 16;
parameter DURATION = 1000;

	reg [15:0]data;
	reg clk;
	reg en;
	wire[MSB-1:0][7:0] out;

shift_16Bit  shift_reg_1(
	.data(data),
	.clk(clk),
	.en(en)
	);

always #1 clk <= ~clk;
always #1 data <= data + 4'b0111;


initial begin
	clk <= 0;
	en <= 0;
	data <= 1;
	#20 en <= 1;

$dumpfile(`DUMPSTR(`VCD_OUTPUT));
  $dumpvars(0, shift_reg_1);

   #(DURATION) $display("End of simulation");
  $finish;
end // initial

endmodule // tb_shift

sim/shiftsim/shift_reg_tb.vcd
$date
	Sat Jun 11 08:35:36 2022
$end
$version
	Icarus Verilog
$end
$timescale
	10ns
$end
$scope module tb_shift $end
$scope module shift_reg_1 $end
$var wire 1 ! clk $end
$var wire 16 " data [15:0] $end
$var wire 1 # en $end
$var reg 16 $ out_0 [15:0] $end
$var reg 16 % out_1 [15:0] $end
$var reg 16 & out_2 [15:0] $end
$var reg 16 ' out_3 [15:0] $end
$var reg 16 ( out_4 [15:0] $end
$var reg 16 ) out_5 [15:0] $end
$var reg 16 * out_6 [15:0] $end
$var reg 16 + out_7 [15:0] $end
$upscope $end
$upscope $end
$enddefinitions $end
#200
$dumpvars
bx +
bx *
bx )
bx (
bx '
bx &
bx %
bx $
1#
b10001101 "
0!
$end
#210
b10010100 $
b10010100 "
1!
#220
b10011011 "
0!
#230
b10100010 $
b10010100 %
b10100010 "
1!
#240
b10101001 "
0!
#250
b10110000 $
b10100010 %
b10010100 &
b10110000 "
1!
#260
b10110111 "
0!
#270
b10111110 $
b10110000 %
b10100010 &
b10010100 '
b10111110 "
1!
#280
b11000101 "
0!
#290
b11001100 $
b10111110 %
b10110000 &
b10100010 '
b10010100 (
b11001100 "
1!
#300
b11010011 "
0!
#310
b11011010 $
b11001100 %
b10111110 &
b10110000 '
b10100010 (
b10010100 )
b11011010 "
1!
#320
b11100001 "
0!
#330
b11101000 $
b11011010 %
b11001100 &
b10111110 '
b10110000 (
b10100010 )
b10010100 *
b11101000 "
1!
#340
b11101111 "
0!
#350
b11110110 $
b11101000 %
b11011010 &
b11001100 '
b10111110 (
b10110000 )
b10100010 *
b10010100 +
b11110110 "
1!
#360
b11111101 "
0!
#370
b100000100 $
b11110110 %
b11101000 &
b11011010 '
b11001100 (
b10111110 )
b10110000 *
b10100010 +
b100000100 "
1!
#380
b100001011 "
0!
#390
b100010010 $
b100000100 %
b11110110 &
b11101000 '
b11011010 (
b11001100 )
b10111110 *
b10110000 +
b100010010 "
1!
#400
b100011001 "
0!
#410
b100100000 $
b100010010 %
b100000100 &
b11110110 '
b11101000 (
b11011010 )
b11001100 *
b10111110 +
b100100000 "
1!
#420
b100100111 "
0!
#430
b100101110 $
b100100000 %
b100010010 &
b100000100 '
b11110110 (
b11101000 )
b11011010 *
b11001100 +
b100101110 "
1!
#440
b100110101 "
0!
#450
b100111100 $
b100101110 %
b100100000 &
b100010010 '
b100000100 (
b11110110 )
b11101000 *
b11011010 +
b100111100 "
1!
#460
b101000011 "
0!
#470
b101001010 $
b100111100 %
b100101110 &
b100100000 '
b100010010 (
b100000100 )
b11110110 *
b11101000 +
b101001010 "
1!
#480
b101010001 "
0!
#490
b101011000 $
b101001010 %
b100111100 &
b100101110 '
b100100000 (
b100010010 )
b100000100 *
b11110110 +
b101011000 "
1!
#500
b101011111 "
0!
#510
b101100110 $
b101011000 %
b101001010 &
b100111100 '
b100101110 (
b100100000 )
b100010010 *
b100000100 +
b101100110 "
1!
#520
b101101101 "
0!
#530
b101110100 $
b101100110 %
b101011000 &
b101001010 '
b100111100 (
b100101110 )
b100100000 *
b100010010 +
b101110100 "
1!
#540
b101111011 "
0!
#550
b110000010 $
b101110100 %
b101100110 &
b101011000 '
b101001010 (
b100111100 )
b100101110 *
b100100000 +
b110000010 "
1!
#560
b110001001 "
0!
#570
b110010000 $
b110000010 %
b101110100 &
b101100110 '
b101011000 (
b101001010 )
b100111100 *
b100101110 +
b110010000 "
1!
#580
b110010111 "
0!
#590
b110011110 $
b110010000 %
b110000010 &
b101110100 '
b101100110 (
b101011000 )
b101001010 *
b100111100 +
b110011110 "
1!
#600
b110100101 "
0!
#610
b110101100 $
b110011110 %
b110010000 &
b110000010 '
b101110100 (
b101100110 )
b101011000 *
b101001010 +
b110101100 "
1!
#620
b110110011 "
0!
#630
b110111010 $
b110101100 %
b110011110 &
b110010000 '
b110000010 (
b101110100 )
b101100110 *
b101011000 +
b110111010 "
1!
#640
b111000001 "
0!
#650
b111001000 $
b110111010 %
b110101100 &
b110011110 '
b110010000 (
b110000010 )
b101110100 *
b101100110 +
b111001000 "
1!
#660
b111001111 "
0!
#670
b111010110 $
b111001000 %
b110111010 &
b110101100 '
b110011110 (
b110010000 )
b110000010 *
b101110100 +
b111010110 "
1!
#680
b111011101 "
0!
#690
b111100100 $
b111010110 %
b111001000 &
b110111010 '
b110101100 (
b110011110 )
b110010000 *
b110000010 +
b111100100 "
1!
#700
b111101011 "
0!
#710
b111110010 $
b111100100 %
b111010110 &
b111001000 '
b110111010 (
b110101100 )
b110011110 *
b110010000 +
b111110010 "
1!
#720
b111111001 "
0!
#730
b1000000000 $
b111110010 %
b111100100 &
b111010110 '
b111001000 (
b110111010 )
b110101100 *
b110011110 +
b1000000000 "
1!
#740
b1000000111 "
0!
#750
b1000001110 $
b1000000000 %
b111110010 &
b111100100 '
b111010110 (
b111001000 )
b110111010 *
b110101100 +
b1000001110 "
1!
#760
b1000010101 "
0!
#770
b1000011100 $
b1000001110 %
b1000000000 &
b111110010 '
b111100100 (
b111010110 )
b111001000 *
b110111010 +
b1000011100 "
1!
#780
b1000100011 "
0!
#790
b1000101010 $
b1000011100 %
b1000001110 &
b1000000000 '
b111110010 (
b111100100 )
b111010110 *
b111001000 +
b1000101010 "
1!
#800
b1000110001 "
0!
#810
b1000111000 $
b1000101010 %
b1000011100 &
b1000001110 '
b1000000000 (
b111110010 )
b111100100 *
b111010110 +
b1000111000 "
1!
#820
b1000111111 "
0!
#830
b1001000110 $
b1000111000 %
b1000101010 &
b1000011100 '
b1000001110 (
b1000000000 )
b111110010 *
b111100100 +
b1001000110 "
1!
#840
b1001001101 "
0!
#850
b1001010100 $
b1001000110 %
b1000111000 &
b1000101010 '
b1000011100 (
b1000001110 )
b1000000000 *
b111110010 +
b1001010100 "
1!
#860
b1001011011 "
0!
#870
b1001100010 $
b1001010100 %
b1001000110 &
b1000111000 '
b1000101010 (
b1000011100 )
b1000001110 *
b1000000000 +
b1001100010 "
1!
#880
b1001101001 "
0!
#890
b1001110000 $
b1001100010 %
b1001010100 &
b1001000110 '
b1000111000 (
b1000101010 )
b1000011100 *
b1000001110 +
b1001110000 "
1!
#900
b1001110111 "
0!
#910
b1001111110 $
b1001110000 %
b1001100010 &
b1001010100 '
b1001000110 (
b1000111000 )
b1000101010 *
b1000011100 +
b1001111110 "
1!
#920
b1010000101 "
0!
#930
b1010001100 $
b1001111110 %
b1001110000 &
b1001100010 '
b1001010100 (
b1001000110 )
b1000111000 *
b1000101010 +
b1010001100 "
1!
#940
b1010010011 "
0!
#950
b1010011010 $
b1010001100 %
b1001111110 &
b1001110000 '
b1001100010 (
b1001010100 )
b1001000110 *
b1000111000 +
b1010011010 "
1!
#960
b1010100001 "
0!
#970
b1010101000 $
b1010011010 %
b1010001100 &
b1001111110 '
b1001110000 (
b1001100010 )
b1001010100 *
b1001000110 +
b1010101000 "
1!
#980
b1010101111 "
0!
#990
b1010110110 $
b1010101000 %
b1010011010 &
b1010001100 '
b1001111110 (
b1001110000 )
b1001100010 *
b1001010100 +
b1010110110 "
1!
#1000
b1010111101 "
0!
#1010
b1011000100 $
b1010110110 %
b1010101000 &
b1010011010 '
b1010001100 (
b1001111110 )
b1001110000 *
b1001100010 +
b1011000100 "
1!
#1020
b1011001011 "
0!
#1030
b1011010010 $
b1011000100 %
b1010110110 &
b1010101000 '
b1010011010 (
b1010001100 )
b1001111110 *
b1001110000 +
b1011010010 "
1!
#1040
b1011011001 "
0!
#1050
b1011100000 $
b1011010010 %
b1011000100 &
b1010110110 '
b1010101000 (
b1010011010 )
b1010001100 *
b1001111110 +
b1011100000 "
1!
#1060
b1011100111 "
0!
#1070
b1011101110 $
b1011100000 %
b1011010010 &
b1011000100 '
b1010110110 (
b1010101000 )
b1010011010 *
b1010001100 +
b1011101110 "
1!
#1080
b1011110101 "
0!
#1090
b1011111100 $
b1011101110 %
b1011100000 &
b1011010010 '
b1011000100 (
b1010110110 )
b1010101000 *
b1010011010 +
b1011111100 "
1!
#1100
b1100000011 "
0!
#1110
b1100001010 $
b1011111100 %
b1011101110 &
b1011100000 '
b1011010010 (
b1011000100 )
b1010110110 *
b1010101000 +
b1100001010 "
1!
#1120
b1100010001 "
0!
#1130
b1100011000 $
b1100001010 %
b1011111100 &
b1011101110 '
b1011100000 (
b1011010010 )
b1011000100 *
b1010110110 +
b1100011000 "
1!
#1140
b1100011111 "
0!
#1150
b1100100110 $
b1100011000 %
b1100001010 &
b1011111100 '
b1011101110 (
b1011100000 )
b1011010010 *
b1011000100 +
b1100100110 "
1!
#1160
b1100101101 "
0!
#1170
b1100110100 $
b1100100110 %
b1100011000 &
b1100001010 '
b1011111100 (
b1011101110 )
b1011100000 *
b1011010010 +
b1100110100 "
1!
#1180
b1100111011 "
0!
#1190
b1101000010 $
b1100110100 %
b1100100110 &
b1100011000 '
b1100001010 (
b1011111100 )
b1011101110 *
b1011100000 +
b1101000010 "
1!
#1200
b1101001001 "
0!
#1210
b1101010000 $
b1101000010 %
b1100110100 &
b1100100110 '
b1100011000 (
b1100001010 )
b1011111100 *
b1011101110 +
b1101010000 "
1!
#1220
b1101010111 "
0!
#1230
b1101011110 $
b1101010000 %
b1101000010 &
b1100110100 '
b1100100110 (
b1100011000 )
b1100001010 *
b1011111100 +
b1101011110 "
1!
#1240
b1101100101 "
0!
#1250
b1101101100 $
b1101011110 %
b1101010000 &
b1101000010 '
b1100110100 (
b1100100110 )
b1100011000 *
b1100001010 +
b1101101100 "
1!
#1260
b1101110011 "
0!
#1270
b1101111010 $
b1101101100 %
b1101011110 &
b1101010000 '
b1101000010 (
b1100110100 )
b1100100110 *
b1100011000 +
b1101111010 "
1!
#1280
b1110000001 "
0!
#1290
b1110001000 $
b1101111010 %
b1101101100 &
b1101011110 '
b1101010000 (
b1101000010 )
b1100110100 *
b1100100110 +
b1110001000 "
1!
#1300
b1110001111 "
0!
#1310
b1110010110 $
b1110001000 %
b1101111010 &
b1101101100 '
b1101011110 (
b1101010000 )
b1101000010 *
b1100110100 +
b1110010110 "
1!
#1320
b1110011101 "
0!
#1330
b1110100100 $
b1110010110 %
b1110001000 &
b1101111010 '
b1101101100 (
b1101011110 )
b1101010000 *
b1101000010 +
b1110100100 "
1!
#1340
b1110101011 "
0!
#1350
b1110110010 $
b1110100100 %
b1110010110 &
b1110001000 '
b1101111010 (
b1101101100 )
b1101011110 *
b1101010000 +
b1110110010 "
1!
#1360
b1110111001 "
0!
#1370
b1111000000 $
b1110110010 %
b1110100100 &
b1110010110 '
b1110001000 (
b1101111010 )
b1101101100 *
b1101011110 +
b1111000000 "
1!
#1380
b1111000111 "
0!
#1390
b1111001110 $
b1111000000 %
b1110110010 &
b1110100100 '
b1110010110 (
b1110001000 )
b1101111010 *
b1101101100 +
b1111001110 "
1!
#1400
b1111010101 "
0!
#1410
b1111011100 $
b1111001110 %
b1111000000 &
b1110110010 '
b1110100100 (
b1110010110 )
b1110001000 *
b1101111010 +
b1111011100 "
1!
#1420
b1111100011 "
0!
#1430
b1111101010 $
b1111011100 %
b1111001110 &
b1111000000 '
b1110110010 (
b1110100100 )
b1110010110 *
b1110001000 +
b1111101010 "
1!
#1440
b1111110001 "
0!
#1450
b1111111000 $
b1111101010 %
b1111011100 &
b1111001110 '
b1111000000 (
b1110110010 )
b1110100100 *
b1110010110 +
b1111111000 "
1!
#1460
b1111111111 "
0!
#1470
b10000000110 $
b1111111000 %
b1111101010 &
b1111011100 '
b1111001110 (
b1111000000 )
b1110110010 *
b1110100100 +
b10000000110 "
1!
#1480
b10000001101 "
0!
#1490
b10000010100 $
b10000000110 %
b1111111000 &
b1111101010 '
b1111011100 (
b1111001110 )
b1111000000 *
b1110110010 +
b10000010100 "
1!
#1500
b10000011011 "
0!
#1510
b10000100010 $
b10000010100 %
b10000000110 &
b1111111000 '
b1111101010 (
b1111011100 )
b1111001110 *
b1111000000 +
b10000100010 "
1!
#1520
b10000101001 "
0!
#1530
b10000110000 $
b10000100010 %
b10000010100 &
b10000000110 '
b1111111000 (
b1111101010 )
b1111011100 *
b1111001110 +
b10000110000 "
1!
#1540
b10000110111 "
0!
#1550
b10000111110 $
b10000110000 %
b10000100010 &
b10000010100 '
b10000000110 (
b1111111000 )
b1111101010 *
b1111011100 +
b10000111110 "
1!
#1560
b10001000101 "
0!
#1570
b10001001100 $
b10000111110 %
b10000110000 &
b10000100010 '
b10000010100 (
b10000000110 )
b1111111000 *
b1111101010 +
b10001001100 "
1!
#1580
b10001010011 "
0!
#1590
b10001011010 $
b10001001100 %
b10000111110 &
b10000110000 '
b10000100010 (
b10000010100 )
b10000000110 *
b1111111000 +
b10001011010 "
1!
#1600
b10001100001 "
0!
#1610
b10001101000 $
b10001011010 %
b10001001100 &
b10000111110 '
b10000110000 (
b10000100010 )
b10000010100 *
b10000000110 +
b10001101000 "
1!
#1620
b10001101111 "
0!
#1630
b10001110110 $
b10001101000 %
b10001011010 &
b10001001100 '
b10000111110 (
b10000110000 )
b10000100010 *
b10000010100 +
b10001110110 "
1!
#1640
b10001111101 "
0!
#1650
b10010000100 $
b10001110110 %
b10001101000 &
b10001011010 '
b10001001100 (
b10000111110 )
b10000110000 *
b10000100010 +
b10010000100 "
1!
#1660
b10010001011 "
0!
#1670
b10010010010 $
b10010000100 %
b10001110110 &
b10001101000 '
b10001011010 (
b10001001100 )
b10000111110 *
b10000110000 +
b10010010010 "
1!
#1680
b10010011001 "
0!
#1690
b10010100000 $
b10010010010 %
b10010000100 &
b10001110110 '
b10001101000 (
b10001011010 )
b10001001100 *
b10000111110 +
b10010100000 "
1!
#1700
b10010100111 "
0!
#1710
b10010101110 $
b10010100000 %
b10010010010 &
b10010000100 '
b10001110110 (
b10001101000 )
b10001011010 *
b10001001100 +
b10010101110 "
1!
#1720
b10010110101 "
0!
#1730
b10010111100 $
b10010101110 %
b10010100000 &
b10010010010 '
b10010000100 (
b10001110110 )
b10001101000 *
b10001011010 +
b10010111100 "
1!
#1740
b10011000011 "
0!
#1750
b10011001010 $
b10010111100 %
b10010101110 &
b10010100000 '
b10010010010 (
b10010000100 )
b10001110110 *
b10001101000 +
b10011001010 "
1!
#1760
b10011010001 "
0!
#1770
b10011011000 $
b10011001010 %
b10010111100 &
b10010101110 '
b10010100000 (
b10010010010 )
b10010000100 *
b10001110110 +
b10011011000 "
1!
#1780
b10011011111 "
0!
#1790
b10011100110 $
b10011011000 %
b10011001010 &
b10010111100 '
b10010101110 (
b10010100000 )
b10010010010 *
b10010000100 +
b10011100110 "
1!
#1800
b10011101101 "
0!
#1810
b10011110100 $
b10011100110 %
b10011011000 &
b10011001010 '
b10010111100 (
b10010101110 )
b10010100000 *
b10010010010 +
b10011110100 "
1!
#1820
b10011111011 "
0!
#1830
b10100000010 $
b10011110100 %
b10011100110 &
b10011011000 '
b10011001010 (
b10010111100 )
b10010101110 *
b10010100000 +
b10100000010 "
1!
#1840
b10100001001 "
0!
#1850
b10100010000 $
b10100000010 %
b10011110100 &
b10011100110 '
b10011011000 (
b10011001010 )
b10010111100 *
b10010101110 +
b10100010000 "
1!
#1860
b10100010111 "
0!
#1870
b10100011110 $
b10100010000 %
b10100000010 &
b10011110100 '
b10011100110 (
b10011011000 )
b10011001010 *
b10010111100 +
b10100011110 "
1!
#1880
b10100100101 "
0!
#1890
b10100101100 $
b10100011110 %
b10100010000 &
b10100000010 '
b10011110100 (
b10011100110 )
b10011011000 *
b10011001010 +
b10100101100 "
1!
#1900
b10100110011 "
0!
#1910
b10100111010 $
b10100101100 %
b10100011110 &
b10100010000 '
b10100000010 (
b10011110100 )
b10011100110 *
b10011011000 +
b10100111010 "
1!
#1920
b10101000001 "
0!
#1930
b10101001000 $
b10100111010 %
b10100101100 &
b10100011110 '
b10100010000 (
b10100000010 )
b10011110100 *
b10011100110 +
b10101001000 "
1!
#1940
b10101001111 "
0!
#1950
b10101010110 $
b10101001000 %
b10100111010 &
b10100101100 '
b10100011110 (
b10100010000 )
b10100000010 *
b10011110100 +
b10101010110 "
1!
#1960
b10101011101 "
0!
#1970
b10101100100 $
b10101010110 %
b10101001000 &
b10100111010 '
b10100101100 (
b10100011110 )
b10100010000 *
b10100000010 +
b10101100100 "
1!
#1980
b10101101011 "
0!
#1990
b10101110010 $
b10101100100 %
b10101010110 &
b10101001000 '
b10100111010 (
b10100101100 )
b10100011110 *
b10100010000 +
b10101110010 "
1!
#2000
b10101111001 "
0!
#2010
b10110000000 $
b10101110010 %
b10101100100 &
b10101010110 '
b10101001000 (
b10100111010 )
b10100101100 *
b10100011110 +
b10110000000 "
1!
#2020
b10110000111 "
0!
#2030
b10110001110 $
b10110000000 %
b10101110010 &
b10101100100 '
b10101010110 (
b10101001000 )
b10100111010 *
b10100101100 +
b10110001110 "
1!
#2040
b10110010101 "
0!
#2050
b10110011100 $
b10110001110 %
b10110000000 &
b10101110010 '
b10101100100 (
b10101010110 )
b10101001000 *
b10100111010 +
b10110011100 "
1!
#2060
b10110100011 "
0!
#2070
b10110101010 $
b10110011100 %
b10110001110 &
b10110000000 '
b10101110010 (
b10101100100 )
b10101010110 *
b10101001000 +
b10110101010 "
1!
#2080
b10110110001 "
0!
#2090
b10110111000 $
b10110101010 %
b10110011100 &
b10110001110 '
b10110000000 (
b10101110010 )
b10101100100 *
b10101010110 +
b10110111000 "
1!
#2100
b10110111111 "
0!
#2110
b10111000110 $
b10110111000 %
b10110101010 &
b10110011100 '
b10110001110 (
b10110000000 )
b10101110010 *
b10101100100 +
b10111000110 "
1!
#2120
b10111001101 "
0!
#2130
b10111010100 $
b10111000110 %
b10110111000 &
b10110101010 '
b10110011100 (
b10110001110 )
b10110000000 *
b10101110010 +
b10111010100 "
1!
#2140
b10111011011 "
0!
#2150
b10111100010 $
b10111010100 %
b10111000110 &
b10110111000 '
b10110101010 (
b10110011100 )
b10110001110 *
b10110000000 +
b10111100010 "
1!
#2160
b10111101001 "
0!
#2170
b10111110000 $
b10111100010 %
b10111010100 &
b10111000110 '
b10110111000 (
b10110101010 )
b10110011100 *
b10110001110 +
b10111110000 "
1!
#2180
b10111110111 "
0!
#2190
b10111111110 $
b10111110000 %
b10111100010 &
b10111010100 '
b10111000110 (
b10110111000 )
b10110101010 *
b10110011100 +
b10111111110 "
1!
#2200
b11000000101 "
0!
#2210
b11000001100 $
b10111111110 %
b10111110000 &
b10111100010 '
b10111010100 (
b10111000110 )
b10110111000 *
b10110101010 +
b11000001100 "
1!
#2220
b11000010011 "
0!
#2230
b11000011010 $
b11000001100 %
b10111111110 &
b10111110000 '
b10111100010 (
b10111010100 )
b10111000110 *
b10110111000 +
b11000011010 "
1!
#2240
b11000100001 "
0!
#2250
b11000101000 $
b11000011010 %
b11000001100 &
b10111111110 '
b10111110000 (
b10111100010 )
b10111010100 *
b10111000110 +
b11000101000 "
1!
#2260
b11000101111 "
0!
#2270
b11000110110 $
b11000101000 %
b11000011010 &
b11000001100 '
b10111111110 (
b10111110000 )
b10111100010 *
b10111010100 +
b11000110110 "
1!
#2280
b11000111101 "
0!
#2290
b11001000100 $
b11000110110 %
b11000101000 &
b11000011010 '
b11000001100 (
b10111111110 )
b10111110000 *
b10111100010 +
b11001000100 "
1!
#2300
b11001001011 "
0!
#2310
b11001010010 $
b11001000100 %
b11000110110 &
b11000101000 '
b11000011010 (
b11000001100 )
b10111111110 *
b10111110000 +
b11001010010 "
1!
#2320
b11001011001 "
0!
#2330
b11001100000 $
b11001010010 %
b11001000100 &
b11000110110 '
b11000101000 (
b11000011010 )
b11000001100 *
b10111111110 +
b11001100000 "
1!
#2340
b11001100111 "
0!
#2350
b11001101110 $
b11001100000 %
b11001010010 &
b11001000100 '
b11000110110 (
b11000101000 )
b11000011010 *
b11000001100 +
b11001101110 "
1!
#2360
b11001110101 "
0!
#2370
b11001111100 $
b11001101110 %
b11001100000 &
b11001010010 '
b11001000100 (
b11000110110 )
b11000101000 *
b11000011010 +
b11001111100 "
1!
#2380
b11010000011 "
0!
#2390
b11010001010 $
b11001111100 %
b11001101110 &
b11001100000 '
b11001010010 (
b11001000100 )
b11000110110 *
b11000101000 +
b11010001010 "
1!
#2400
b11010010001 "
0!
#2410
b11010011000 $
b11010001010 %
b11001111100 &
b11001101110 '
b11001100000 (
b11001010010 )
b11001000100 *
b11000110110 +
b11010011000 "
1!
#2420
b11010011111 "
0!
#2430
b11010100110 $
b11010011000 %
b11010001010 &
b11001111100 '
b11001101110 (
b11001100000 )
b11001010010 *
b11001000100 +
b11010100110 "
1!
#2440
b11010101101 "
0!
#2450
b11010110100 $
b11010100110 %
b11010011000 &
b11010001010 '
b11001111100 (
b11001101110 )
b11001100000 *
b11001010010 +
b11010110100 "
1!
#2460
b11010111011 "
0!
#2470
b11011000010 $
b11010110100 %
b11010100110 &
b11010011000 '
b11010001010 (
b11001111100 )
b11001101110 *
b11001100000 +
b11011000010 "
1!
#2480
b11011001001 "
0!
#2490
b11011010000 $
b11011000010 %
b11010110100 &
b11010100110 '
b11010011000 (
b11010001010 )
b11001111100 *
b11001101110 +
b11011010000 "
1!
#2500
b11011010111 "
0!
#2510
b11011011110 $
b11011010000 %
b11011000010 &
b11010110100 '
b11010100110 (
b11010011000 )
b11010001010 *
b11001111100 +
b11011011110 "
1!
#2520
b11011100101 "
0!
#2530
b11011101100 $
b11011011110 %
b11011010000 &
b11011000010 '
b11010110100 (
b11010100110 )
b11010011000 *
b11010001010 +
b11011101100 "
1!
#2540
b11011110011 "
0!
#2550
b11011111010 $
b11011101100 %
b11011011110 &
b11011010000 '
b11011000010 (
b11010110100 )
b11010100110 *
b11010011000 +
b11011111010 "
1!
#2560
b11100000001 "
0!
#2570
b11100001000 $
b11011111010 %
b11011101100 &
b11011011110 '
b11011010000 (
b11011000010 )
b11010110100 *
b11010100110 +
b11100001000 "
1!
#2580
b11100001111 "
0!
#2590
b11100010110 $
b11100001000 %
b11011111010 &
b11011101100 '
b11011011110 (
b11011010000 )
b11011000010 *
b11010110100 +
b11100010110 "
1!
#2600
b11100011101 "
0!
#2610
b11100100100 $
b11100010110 %
b11100001000 &
b11011111010 '
b11011101100 (
b11011011110 )
b11011010000 *
b11011000010 +
b11100100100 "
1!
#2620
b11100101011 "
0!
#2630
b11100110010 $
b11100100100 %
b11100010110 &
b11100001000 '
b11011111010 (
b11011101100 )
b11011011110 *
b11011010000 +
b11100110010 "
1!
#2640
b11100111001 "
0!
#2650
b11101000000 $
b11100110010 %
b11100100100 &
b11100010110 '
b11100001000 (
b11011111010 )
b11011101100 *
b11011011110 +
b11101000000 "
1!
#2660
b11101000111 "
0!
#2670
b11101001110 $
b11101000000 %
b11100110010 &
b11100100100 '
b11100010110 (
b11100001000 )
b11011111010 *
b11011101100 +
b11101001110 "
1!
#2680
b11101010101 "
0!
#2690
b11101011100 $
b11101001110 %
b11101000000 &
b11100110010 '
b11100100100 (
b11100010110 )
b11100001000 *
b11011111010 +
b11101011100 "
1!
#2700
b11101100011 "
0!
#2710
b11101101010 $
b11101011100 %
b11101001110 &
b11101000000 '
b11100110010 (
b11100100100 )
b11100010110 *
b11100001000 +
b11101101010 "
1!
#2720
b11101110001 "
0!
#2730
b11101111000 $
b11101101010 %
b11101011100 &
b11101001110 '
b11101000000 (
b11100110010 )
b11100100100 *
b11100010110 +
b11101111000 "
1!
#2740
b11101111111 "
0!
#2750
b11110000110 $
b11101111000 %
b11101101010 &
b11101011100 '
b11101001110 (
b11101000000 )
b11100110010 *
b11100100100 +
b11110000110 "
1!
#2760
b11110001101 "
0!
#2770
b11110010100 $
b11110000110 %
b11101111000 &
b11101101010 '
b11101011100 (
b11101001110 )
b11101000000 *
b11100110010 +
b11110010100 "
1!
#2780
b11110011011 "
0!
#2790
b11110100010 $
b11110010100 %
b11110000110 &
b11101111000 '
b11101101010 (
b11101011100 )
b11101001110 *
b11101000000 +
b11110100010 "
1!
#2800
b11110101001 "
0!
#2810
b11110110000 $
b11110100010 %
b11110010100 &
b11110000110 '
b11101111000 (
b11101101010 )
b11101011100 *
b11101001110 +
b11110110000 "
1!
#2820
b11110110111 "
0!
#2830
b11110111110 $
b11110110000 %
b11110100010 &
b11110010100 '
b11110000110 (
b11101111000 )
b11101101010 *
b11101011100 +
b11110111110 "
1!
#2840
b11111000101 "
0!
#2850
b11111001100 $
b11110111110 %
b11110110000 &
b11110100010 '
b11110010100 (
b11110000110 )
b11101111000 *
b11101101010 +
b11111001100 "
1!
#2860
b11111010011 "
0!
#2870
b11111011010 $
b11111001100 %
b11110111110 &
b11110110000 '
b11110100010 (
b11110010100 )
b11110000110 *
b11101111000 +
b11111011010 "
1!
#2880
b11111100001 "
0!
#2890
b11111101000 $
b11111011010 %
b11111001100 &
b11110111110 '
b11110110000 (
b11110100010 )
b11110010100 *
b11110000110 +
b11111101000 "
1!
#2900
b11111101111 "
0!
#2910
b11111110110 $
b11111101000 %
b11111011010 &
b11111001100 '
b11110111110 (
b11110110000 )
b11110100010 *
b11110010100 +
b11111110110 "
1!
#2920
b11111111101 "
0!
#2930
b100000000100 $
b11111110110 %
b11111101000 &
b11111011010 '
b11111001100 (
b11110111110 )
b11110110000 *
b11110100010 +
b100000000100 "
1!
#2940
b100000001011 "
0!
#2950
b100000010010 $
b100000000100 %
b11111110110 &
b11111101000 '
b11111011010 (
b11111001100 )
b11110111110 *
b11110110000 +
b100000010010 "
1!
#2960
b100000011001 "
0!
#2970
b100000100000 $
b100000010010 %
b100000000100 &
b11111110110 '
b11111101000 (
b11111011010 )
b11111001100 *
b11110111110 +
b100000100000 "
1!
#2980
b100000100111 "
0!
#2990
b100000101110 $
b100000100000 %
b100000010010 &
b100000000100 '
b11111110110 (
b11111101000 )
b11111011010 *
b11111001100 +
b100000101110 "
1!
#3000
b100000110101 "
0!
#3010
b100000111100 $
b100000101110 %
b100000100000 &
b100000010010 '
b100000000100 (
b11111110110 )
b11111101000 *
b11111011010 +
b100000111100 "
1!
#3020
b100001000011 "
0!
#3030
b100001001010 $
b100000111100 %
b100000101110 &
b100000100000 '
b100000010010 (
b100000000100 )
b11111110110 *
b11111101000 +
b100001001010 "
1!
#3040
b100001010001 "
0!
#3050
b100001011000 $
b100001001010 %
b100000111100 &
b100000101110 '
b100000100000 (
b100000010010 )
b100000000100 *
b11111110110 +
b100001011000 "
1!
#3060
b100001011111 "
0!
#3070
b100001100110 $
b100001011000 %
b100001001010 &
b100000111100 '
b100000101110 (
b100000100000 )
b100000010010 *
b100000000100 +
b100001100110 "
1!
#3080
b100001101101 "
0!
#3090
b100001110100 $
b100001100110 %
b100001011000 &
b100001001010 '
b100000111100 (
b100000101110 )
b100000100000 *
b100000010010 +
b100001110100 "
1!
#3100
b100001111011 "
0!
#3110
b100010000010 $
b100001110100 %
b100001100110 &
b100001011000 '
b100001001010 (
b100000111100 )
b100000101110 *
b100000100000 +
b100010000010 "
1!
#3120
b100010001001 "
0!
#3130
b100010010000 $
b100010000010 %
b100001110100 &
b100001100110 '
b100001011000 (
b100001001010 )
b100000111100 *
b100000101110 +
b100010010000 "
1!
#3140
b100010010111 "
0!
#3150
b100010011110 $
b100010010000 %
b100010000010 &
b100001110100 '
b100001100110 (
b100001011000 )
b100001001010 *
b100000111100 +
b100010011110 "
1!
#3160
b100010100101 "
0!
#3170
b100010101100 $
b100010011110 %
b100010010000 &
b100010000010 '
b100001110100 (
b100001100110 )
b100001011000 *
b100001001010 +
b100010101100 "
1!
#3180
b100010110011 "
0!
#3190
b100010111010 $
b100010101100 %
b100010011110 &
b100010010000 '
b100010000010 (
b100001110100 )
b100001100110 *
b100001011000 +
b100010111010 "
1!
#3200
b100011000001 "
0!
#3210
b100011001000 $
b100010111010 %
b100010101100 &
b100010011110 '
b100010010000 (
b100010000010 )
b100001110100 *
b100001100110 +
b100011001000 "
1!
#3220
b100011001111 "
0!
#3230
b100011010110 $
b100011001000 %
b100010111010 &
b100010101100 '
b100010011110 (
b100010010000 )
b100010000010 *
b100001110100 +
b100011010110 "
1!
#3240
b100011011101 "
0!
#3250
b100011100100 $
b100011010110 %
b100011001000 &
b100010111010 '
b100010101100 (
b100010011110 )
b100010010000 *
b100010000010 +
b100011100100 "
1!
#3260
b100011101011 "
0!
