FFT_stage/save/input_regs.v
module input_regs #(parameter N=16, parameter MSB=16)
	(
      input clk,
		input we,
		input [$clog2(N)-1:0] addr,
		input [MSB-1:0] data,
      output [N-1:0] [MSB-1:0]  data_out 
		);

reg [N-1:0] [MSB-1:0]  data_regs = 0;

always @(posedge clk)
begin
   if(we)
   begin
      data_regs[addr]  <= data;
   end
end
assign data_out = data_regs;

endmodule // input_regs

FFT_stage/sim/input_regs_tb.v
`define DUMPSTR(x) `"x.vcd`"
`timescale 100 ns / 10 ns

module tb_regs;

parameter DURATION = 1000;

reg [15:0] count;
reg [3:0] addr;

reg clk;

input_regs regs(
.clk(clk),
.we(1'b1),
.addr(addr),
.data(count)
	);

always #1 clk <= ~clk;

initial begin
	clk <= 0;
	count <= 0;
	addr <= 0;
$dumpfile(`DUMPSTR(`VCD_OUTPUT));
  $dumpvars(0, tb_regs);

   #(DURATION) $display("End of simulation");
  $finish;

end

always @ (posedge clk)
	begin
		count <= count + 1'b1;	
		addr <= addr + 1'b1;
	end

endmodule // tb_adder

FFT_stage/sim/input_regs_tb.vcd
$date
	Sat Jul  2 09:57:19 2022
$end
$version
	Icarus Verilog
$end
$timescale
	1ps
$end
$scope module tb_regs $end
$var reg 4 ! addr [3:0] $end
$var reg 1 " clk $end
$var reg 16 # count [15:0] $end
$scope module regs $end
$var wire 4 $ addr [3:0] $end
$var wire 1 " clk $end
$var wire 16 % data [15:0] $end
$var wire 256 & data_out [255:0] $end
$var wire 1 ' we $end
$var reg 256 ( data_regs [255:0] $end
$upscope $end
$upscope $end
$enddefinitions $end
#0
$dumpvars
b0 (
1'
b0 &
b0 %
b0 $
b0 #
0"
b0 !
$end
#100000
b1 !
b1 $
b1 #
b1 %
1"
#200000
0"
#300000
b10 !
b10 $
b10 #
b10 %
b10000000000000000 &
b10000000000000000 (
1"
#400000
0"
#500000
b1000000000000000010000000000000000 &
b1000000000000000010000000000000000 (
b11 !
b11 $
b11 #
b11 %
1"
#600000
0"
#700000
b100 !
b100 $
b100 #
b100 %
b11000000000000001000000000000000010000000000000000 &
b11000000000000001000000000000000010000000000000000 (
1"
#800000
0"
#900000
b1000000000000000011000000000000001000000000000000010000000000000000 &
b1000000000000000011000000000000001000000000000000010000000000000000 (
b101 !
b101 $
b101 #
b101 %
1"
#1000000
0"
#1100000
b110 !
b110 $
b110 #
b110 %
b10100000000000001000000000000000011000000000000001000000000000000010000000000000000 &
b10100000000000001000000000000000011000000000000001000000000000000010000000000000000 (
1"
#1200000
0"
#1300000
b110000000000000010100000000000001000000000000000011000000000000001000000000000000010000000000000000 &
b110000000000000010100000000000001000000000000000011000000000000001000000000000000010000000000000000 (
b111 !
b111 $
b111 #
b111 %
1"
#1400000
0"
#1500000
b1000 !
b1000 $
b1000 #
b1000 %
b1110000000000000110000000000000010100000000000001000000000000000011000000000000001000000000000000010000000000000000 &
b1110000000000000110000000000000010100000000000001000000000000000011000000000000001000000000000000010000000000000000 (
1"
#1600000
0"
#1700000
b100000000000000001110000000000000110000000000000010100000000000001000000000000000011000000000000001000000000000000010000000000000000 &
b100000000000000001110000000000000110000000000000010100000000000001000000000000000011000000000000001000000000000000010000000000000000 (
b1001 !
b1001 $
b1001 #
b1001 %
1"
#1800000
0"
#1900000
b1010 !
b1010 $
b1010 #
b1010 %
b1001000000000000100000000000000001110000000000000110000000000000010100000000000001000000000000000011000000000000001000000000000000010000000000000000 &
b1001000000000000100000000000000001110000000000000110000000000000010100000000000001000000000000000011000000000000001000000000000000010000000000000000 (
1"
#2000000
0"
#2100000
b10100000000000001001000000000000100000000000000001110000000000000110000000000000010100000000000001000000000000000011000000000000001000000000000000010000000000000000 &
b10100000000000001001000000000000100000000000000001110000000000000110000000000000010100000000000001000000000000000011000000000000001000000000000000010000000000000000 (
b1011 !
b1011 $
b1011 #
b1011 %
1"
#2200000
0"
#2300000
b1100 !
b1100 $
b1100 #
b1100 %
b101100000000000010100000000000001001000000000000100000000000000001110000000000000110000000000000010100000000000001000000000000000011000000000000001000000000000000010000000000000000 &
b101100000000000010100000000000001001000000000000100000000000000001110000000000000110000000000000010100000000000001000000000000000011000000000000001000000000000000010000000000000000 (
1"
#2400000
0"
#2500000
b1100000000000000101100000000000010100000000000001001000000000000100000000000000001110000000000000110000000000000010100000000000001000000000000000011000000000000001000000000000000010000000000000000 &
b1100000000000000101100000000000010100000000000001001000000000000100000000000000001110000000000000110000000000000010100000000000001000000000000000011000000000000001000000000000000010000000000000000 (
b1101 !
b1101 $
b1101 #
b1101 %
1"
#2600000
0"
#2700000
b1110 !
b1110 $
b1110 #
b1110 %
b11010000000000001100000000000000101100000000000010100000000000001001000000000000100000000000000001110000000000000110000000000000010100000000000001000000000000000011000000000000001000000000000000010000000000000000 &
b11010000000000001100000000000000101100000000000010100000000000001001000000000000100000000000000001110000000000000110000000000000010100000000000001000000000000000011000000000000001000000000000000010000000000000000 (
1"
#2800000
0"
#2900000
b111000000000000011010000000000001100000000000000101100000000000010100000000000001001000000000000100000000000000001110000000000000110000000000000010100000000000001000000000000000011000000000000001000000000000000010000000000000000 &
b111000000000000011010000000000001100000000000000101100000000000010100000000000001001000000000000100000000000000001110000000000000110000000000000010100000000000001000000000000000011000000000000001000000000000000010000000000000000 (
b1111 !
b1111 $
b1111 #
b1111 %
1"
#3000000
0"
#3100000
b0 !
b0 $
b10000 #
b10000 %
b1111000000000000111000000000000011010000000000001100000000000000101100000000000010100000000000001001000000000000100000000000000001110000000000000110000000000000010100000000000001000000000000000011000000000000001000000000000000010000000000000000 &
b1111000000000000111000000000000011010000000000001100000000000000101100000000000010100000000000001001000000000000100000000000000001110000000000000110000000000000010100000000000001000000000000000011000000000000001000000000000000010000000000000000 (
1"
#3200000
0"
#3300000
b1111000000000000111000000000000011010000000000001100000000000000101100000000000010100000000000001001000000000000100000000000000001110000000000000110000000000000010100000000000001000000000000000011000000000000001000000000000000010000000000010000 &
b1111000000000000111000000000000011010000000000001100000000000000101100000000000010100000000000001001000000000000100000000000000001110000000000000110000000000000010100000000000001000000000000000011000000000000001000000000000000010000000000010000 (
b1 !
b1 $
b10001 #
b10001 %
1"
#3400000
0"
#3500000
b10 !
b10 $
b10010 #
b10010 %
b1111000000000000111000000000000011010000000000001100000000000000101100000000000010100000000000001001000000000000100000000000000001110000000000000110000000000000010100000000000001000000000000000011000000000000001000000000000100010000000000010000 &
b1111000000000000111000000000000011010000000000001100000000000000101100000000000010100000000000001001000000000000100000000000000001110000000000000110000000000000010100000000000001000000000000000011000000000000001000000000000100010000000000010000 (
1"
#3600000
0"
#3700000
b1111000000000000111000000000000011010000000000001100000000000000101100000000000010100000000000001001000000000000100000000000000001110000000000000110000000000000010100000000000001000000000000000011000000000001001000000000000100010000000000010000 &
b1111000000000000111000000000000011010000000000001100000000000000101100000000000010100000000000001001000000000000100000000000000001110000000000000110000000000000010100000000000001000000000000000011000000000001001000000000000100010000000000010000 (
b11 !
b11 $
b10011 #
b10011 %
1"
#3800000
0"
#3900000
b100 !
b100 $
b10100 #
b10100 %
b1111000000000000111000000000000011010000000000001100000000000000101100000000000010100000000000001001000000000000100000000000000001110000000000000110000000000000010100000000000001000000000000010011000000000001001000000000000100010000000000010000 &
b1111000000000000111000000000000011010000000000001100000000000000101100000000000010100000000000001001000000000000100000000000000001110000000000000110000000000000010100000000000001000000000000010011000000000001001000000000000100010000000000010000 (
1"
#4000000
0"
#4100000
b1111000000000000111000000000000011010000000000001100000000000000101100000000000010100000000000001001000000000000100000000000000001110000000000000110000000000000010100000000000101000000000000010011000000000001001000000000000100010000000000010000 &
b1111000000000000111000000000000011010000000000001100000000000000101100000000000010100000000000001001000000000000100000000000000001110000000000000110000000000000010100000000000101000000000000010011000000000001001000000000000100010000000000010000 (
b101 !
b101 $
b10101 #
b10101 %
1"
#4200000
0"
#4300000
b110 !
b110 $
b10110 #
b10110 %
b1111000000000000111000000000000011010000000000001100000000000000101100000000000010100000000000001001000000000000100000000000000001110000000000000110000000000001010100000000000101000000000000010011000000000001001000000000000100010000000000010000 &
b1111000000000000111000000000000011010000000000001100000000000000101100000000000010100000000000001001000000000000100000000000000001110000000000000110000000000001010100000000000101000000000000010011000000000001001000000000000100010000000000010000 (
1"
#4400000
0"
#4500000
b1111000000000000111000000000000011010000000000001100000000000000101100000000000010100000000000001001000000000000100000000000000001110000000000010110000000000001010100000000000101000000000000010011000000000001001000000000000100010000000000010000 &
b1111000000000000111000000000000011010000000000001100000000000000101100000000000010100000000000001001000000000000100000000000000001110000000000010110000000000001010100000000000101000000000000010011000000000001001000000000000100010000000000010000 (
b111 !
b111 $
b10111 #
b10111 %
1"
#4600000
0"
#4700000
b1000 !
b1000 $
b11000 #
b11000 %
b1111000000000000111000000000000011010000000000001100000000000000101100000000000010100000000000001001000000000000100000000000000101110000000000010110000000000001010100000000000101000000000000010011000000000001001000000000000100010000000000010000 &
b1111000000000000111000000000000011010000000000001100000000000000101100000000000010100000000000001001000000000000100000000000000101110000000000010110000000000001010100000000000101000000000000010011000000000001001000000000000100010000000000010000 (
1"
#4800000
0"
#4900000
b1111000000000000111000000000000011010000000000001100000000000000101100000000000010100000000000001001000000000001100000000000000101110000000000010110000000000001010100000000000101000000000000010011000000000001001000000000000100010000000000010000 &
b1111000000000000111000000000000011010000000000001100000000000000101100000000000010100000000000001001000000000001100000000000000101110000000000010110000000000001010100000000000101000000000000010011000000000001001000000000000100010000000000010000 (
b1001 !
b1001 $
b11001 #
b11001 %
1"
#5000000
0"
#5100000
b1010 !
b1010 $
b11010 #
b11010 %
b1111000000000000111000000000000011010000000000001100000000000000101100000000000010100000000000011001000000000001100000000000000101110000000000010110000000000001010100000000000101000000000000010011000000000001001000000000000100010000000000010000 &
b1111000000000000111000000000000011010000000000001100000000000000101100000000000010100000000000011001000000000001100000000000000101110000000000010110000000000001010100000000000101000000000000010011000000000001001000000000000100010000000000010000 (
1"
#5200000
0"
#5300000
b1111000000000000111000000000000011010000000000001100000000000000101100000000000110100000000000011001000000000001100000000000000101110000000000010110000000000001010100000000000101000000000000010011000000000001001000000000000100010000000000010000 &
b1111000000000000111000000000000011010000000000001100000000000000101100000000000110100000000000011001000000000001100000000000000101110000000000010110000000000001010100000000000101000000000000010011000000000001001000000000000100010000000000010000 (
b1011 !
b1011 $
b11011 #
b11011 %
1"
#5400000
0"
#5500000
b1100 !
b1100 $
b11100 #
b11100 %
b1111000000000000111000000000000011010000000000001100000000000001101100000000000110100000000000011001000000000001100000000000000101110000000000010110000000000001010100000000000101000000000000010011000000000001001000000000000100010000000000010000 &
b1111000000000000111000000000000011010000000000001100000000000001101100000000000110100000000000011001000000000001100000000000000101110000000000010110000000000001010100000000000101000000000000010011000000000001001000000000000100010000000000010000 (
1"
#5600000
0"
#5700000
b1111000000000000111000000000000011010000000000011100000000000001101100000000000110100000000000011001000000000001100000000000000101110000000000010110000000000001010100000000000101000000000000010011000000000001001000000000000100010000000000010000 &
b1111000000000000111000000000000011010000000000011100000000000001101100000000000110100000000000011001000000000001100000000000000101110000000000010110000000000001010100000000000101000000000000010011000000000001001000000000000100010000000000010000 (
b1101 !
b1101 $
b11101 #
b11101 %
1"
#5800000
0"
#5900000
b1110 !
b1110 $
b11110 #
b11110 %
b1111000000000000111000000000000111010000000000011100000000000001101100000000000110100000000000011001000000000001100000000000000101110000000000010110000000000001010100000000000101000000000000010011000000000001001000000000000100010000000000010000 &
b1111000000000000111000000000000111010000000000011100000000000001101100000000000110100000000000011001000000000001100000000000000101110000000000010110000000000001010100000000000101000000000000010011000000000001001000000000000100010000000000010000 (
1"
#6000000
0"
#6100000
b1111000000000001111000000000000111010000000000011100000000000001101100000000000110100000000000011001000000000001100000000000000101110000000000010110000000000001010100000000000101000000000000010011000000000001001000000000000100010000000000010000 &
b1111000000000001111000000000000111010000000000011100000000000001101100000000000110100000000000011001000000000001100000000000000101110000000000010110000000000001010100000000000101000000000000010011000000000001001000000000000100010000000000010000 (
b1111 !
b1111 $
b11111 #
b11111 %
1"
#6200000
0"
#6300000
b0 !
b0 $
b100000 #
b100000 %
b11111000000000001111000000000000111010000000000011100000000000001101100000000000110100000000000011001000000000001100000000000000101110000000000010110000000000001010100000000000101000000000000010011000000000001001000000000000100010000000000010000 &
b11111000000000001111000000000000111010000000000011100000000000001101100000000000110100000000000011001000000000001100000000000000101110000000000010110000000000001010100000000000101000000000000010011000000000001001000000000000100010000000000010000 (
1"
#6400000
0"
#6500000
b11111000000000001111000000000000111010000000000011100000000000001101100000000000110100000000000011001000000000001100000000000000101110000000000010110000000000001010100000000000101000000000000010011000000000001001000000000000100010000000000100000 &
b11111000000000001111000000000000111010000000000011100000000000001101100000000000110100000000000011001000000000001100000000000000101110000000000010110000000000001010100000000000101000000000000010011000000000001001000000000000100010000000000100000 (
b1 !
b1 $
b100001 #
b100001 %
1"
#6600000
0"
#6700000
b10 !
b10 $
b100010 #
b100010 %
b11111000000000001111000000000000111010000000000011100000000000001101100000000000110100000000000011001000000000001100000000000000101110000000000010110000000000001010100000000000101000000000000010011000000000001001000000000001000010000000000100000 &
b11111000000000001111000000000000111010000000000011100000000000001101100000000000110100000000000011001000000000001100000000000000101110000000000010110000000000001010100000000000101000000000000010011000000000001001000000000001000010000000000100000 (
1"
#6800000
0"
#6900000
b11111000000000001111000000000000111010000000000011100000000000001101100000000000110100000000000011001000000000001100000000000000101110000000000010110000000000001010100000000000101000000000000010011000000000010001000000000001000010000000000100000 &
b11111000000000001111000000000000111010000000000011100000000000001101100000000000110100000000000011001000000000001100000000000000101110000000000010110000000000001010100000000000101000000000000010011000000000010001000000000001000010000000000100000 (
b11 !
b11 $
b100011 #
b100011 %
1"
#7000000
0"
#7100000
b100 !
b100 $
b100100 #
b100100 %
b11111000000000001111000000000000111010000000000011100000000000001101100000000000110100000000000011001000000000001100000000000000101110000000000010110000000000001010100000000000101000000000000100011000000000010001000000000001000010000000000100000 &
b11111000000000001111000000000000111010000000000011100000000000001101100000000000110100000000000011001000000000001100000000000000101110000000000010110000000000001010100000000000101000000000000100011000000000010001000000000001000010000000000100000 (
1"
#7200000
0"
#7300000
b11111000000000001111000000000000111010000000000011100000000000001101100000000000110100000000000011001000000000001100000000000000101110000000000010110000000000001010100000000001001000000000000100011000000000010001000000000001000010000000000100000 &
b11111000000000001111000000000000111010000000000011100000000000001101100000000000110100000000000011001000000000001100000000000000101110000000000010110000000000001010100000000001001000000000000100011000000000010001000000000001000010000000000100000 (
b101 !
b101 $
b100101 #
b100101 %
1"
#7400000
0"
#7500000
b110 !
b110 $
b100110 #
b100110 %
b11111000000000001111000000000000111010000000000011100000000000001101100000000000110100000000000011001000000000001100000000000000101110000000000010110000000000010010100000000001001000000000000100011000000000010001000000000001000010000000000100000 &
b11111000000000001111000000000000111010000000000011100000000000001101100000000000110100000000000011001000000000001100000000000000101110000000000010110000000000010010100000000001001000000000000100011000000000010001000000000001000010000000000100000 (
1"
#7600000
0"
#7700000
b11111000000000001111000000000000111010000000000011100000000000001101100000000000110100000000000011001000000000001100000000000000101110000000000100110000000000010010100000000001001000000000000100011000000000010001000000000001000010000000000100000 &
b11111000000000001111000000000000111010000000000011100000000000001101100000000000110100000000000011001000000000001100000000000000101110000000000100110000000000010010100000000001001000000000000100011000000000010001000000000001000010000000000100000 (
b111 !
b111 $
b100111 #
b100111 %
1"
#7800000
0"
#7900000
b1000 !
b1000 $
b101000 #
b101000 %
b11111000000000001111000000000000111010000000000011100000000000001101100000000000110100000000000011001000000000001100000000000001001110000000000100110000000000010010100000000001001000000000000100011000000000010001000000000001000010000000000100000 &
b11111000000000001111000000000000111010000000000011100000000000001101100000000000110100000000000011001000000000001100000000000001001110000000000100110000000000010010100000000001001000000000000100011000000000010001000000000001000010000000000100000 (
1"
#8000000
0"
#8100000
b11111000000000001111000000000000111010000000000011100000000000001101100000000000110100000000000011001000000000010100000000000001001110000000000100110000000000010010100000000001001000000000000100011000000000010001000000000001000010000000000100000 &
b11111000000000001111000000000000111010000000000011100000000000001101100000000000110100000000000011001000000000010100000000000001001110000000000100110000000000010010100000000001001000000000000100011000000000010001000000000001000010000000000100000 (
b1001 !
b1001 $
b101001 #
b101001 %
1"
#8200000
0"
#8300000
b1010 !
b1010 $
b101010 #
b101010 %
b11111000000000001111000000000000111010000000000011100000000000001101100000000000110100000000000101001000000000010100000000000001001110000000000100110000000000010010100000000001001000000000000100011000000000010001000000000001000010000000000100000 &
b11111000000000001111000000000000111010000000000011100000000000001101100000000000110100000000000101001000000000010100000000000001001110000000000100110000000000010010100000000001001000000000000100011000000000010001000000000001000010000000000100000 (
1"
#8400000
0"
#8500000
b11111000000000001111000000000000111010000000000011100000000000001101100000000001010100000000000101001000000000010100000000000001001110000000000100110000000000010010100000000001001000000000000100011000000000010001000000000001000010000000000100000 &
b11111000000000001111000000000000111010000000000011100000000000001101100000000001010100000000000101001000000000010100000000000001001110000000000100110000000000010010100000000001001000000000000100011000000000010001000000000001000010000000000100000 (
b1011 !
b1011 $
b101011 #
b101011 %
1"
#8600000
0"
#8700000
b1100 !
b1100 $
b101100 #
b101100 %
b11111000000000001111000000000000111010000000000011100000000000010101100000000001010100000000000101001000000000010100000000000001001110000000000100110000000000010010100000000001001000000000000100011000000000010001000000000001000010000000000100000 &
b11111000000000001111000000000000111010000000000011100000000000010101100000000001010100000000000101001000000000010100000000000001001110000000000100110000000000010010100000000001001000000000000100011000000000010001000000000001000010000000000100000 (
1"
#8800000
0"
#8900000
b11111000000000001111000000000000111010000000000101100000000000010101100000000001010100000000000101001000000000010100000000000001001110000000000100110000000000010010100000000001001000000000000100011000000000010001000000000001000010000000000100000 &
b11111000000000001111000000000000111010000000000101100000000000010101100000000001010100000000000101001000000000010100000000000001001110000000000100110000000000010010100000000001001000000000000100011000000000010001000000000001000010000000000100000 (
b1101 !
b1101 $
b101101 #
b101101 %
1"
#9000000
0"
#9100000
b1110 !
b1110 $
b101110 #
b101110 %
b11111000000000001111000000000001011010000000000101100000000000010101100000000001010100000000000101001000000000010100000000000001001110000000000100110000000000010010100000000001001000000000000100011000000000010001000000000001000010000000000100000 &
b11111000000000001111000000000001011010000000000101100000000000010101100000000001010100000000000101001000000000010100000000000001001110000000000100110000000000010010100000000001001000000000000100011000000000010001000000000001000010000000000100000 (
1"
#9200000
0"
#9300000
b11111000000000010111000000000001011010000000000101100000000000010101100000000001010100000000000101001000000000010100000000000001001110000000000100110000000000010010100000000001001000000000000100011000000000010001000000000001000010000000000100000 &
b11111000000000010111000000000001011010000000000101100000000000010101100000000001010100000000000101001000000000010100000000000001001110000000000100110000000000010010100000000001001000000000000100011000000000010001000000000001000010000000000100000 (
b1111 !
b1111 $
b101111 #
b101111 %
1"
#9400000
0"
#9500000
b0 !
b0 $
b110000 #
b110000 %
b101111000000000010111000000000001011010000000000101100000000000010101100000000001010100000000000101001000000000010100000000000001001110000000000100110000000000010010100000000001001000000000000100011000000000010001000000000001000010000000000100000 &
b101111000000000010111000000000001011010000000000101100000000000010101100000000001010100000000000101001000000000010100000000000001001110000000000100110000000000010010100000000001001000000000000100011000000000010001000000000001000010000000000100000 (
1"
#9600000
0"
#9700000
b101111000000000010111000000000001011010000000000101100000000000010101100000000001010100000000000101001000000000010100000000000001001110000000000100110000000000010010100000000001001000000000000100011000000000010001000000000001000010000000000110000 &
b101111000000000010111000000000001011010000000000101100000000000010101100000000001010100000000000101001000000000010100000000000001001110000000000100110000000000010010100000000001001000000000000100011000000000010001000000000001000010000000000110000 (
b1 !
b1 $
b110001 #
b110001 %
1"
#9800000
0"
#9900000
b10 !
b10 $
b110010 #
b110010 %
b101111000000000010111000000000001011010000000000101100000000000010101100000000001010100000000000101001000000000010100000000000001001110000000000100110000000000010010100000000001001000000000000100011000000000010001000000000001100010000000000110000 &
b101111000000000010111000000000001011010000000000101100000000000010101100000000001010100000000000101001000000000010100000000000001001110000000000100110000000000010010100000000001001000000000000100011000000000010001000000000001100010000000000110000 (
1"
#10000000
0"
#10100000
b101111000000000010111000000000001011010000000000101100000000000010101100000000001010100000000000101001000000000010100000000000001001110000000000100110000000000010010100000000001001000000000000100011000000000011001000000000001100010000000000110000 &
b101111000000000010111000000000001011010000000000101100000000000010101100000000001010100000000000101001000000000010100000000000001001110000000000100110000000000010010100000000001001000000000000100011000000000011001000000000001100010000000000110000 (
b11 !
b11 $
b110011 #
b110011 %
1"
#10200000
0"
#10300000
b100 !
b100 $
b110100 #
b110100 %
b101111000000000010111000000000001011010000000000101100000000000010101100000000001010100000000000101001000000000010100000000000001001110000000000100110000000000010010100000000001001000000000000110011000000000011001000000000001100010000000000110000 &
b101111000000000010111000000000001011010000000000101100000000000010101100000000001010100000000000101001000000000010100000000000001001110000000000100110000000000010010100000000001001000000000000110011000000000011001000000000001100010000000000110000 (
1"
#10400000
0"
#10500000
b101111000000000010111000000000001011010000000000101100000000000010101100000000001010100000000000101001000000000010100000000000001001110000000000100110000000000010010100000000001101000000000000110011000000000011001000000000001100010000000000110000 &
b101111000000000010111000000000001011010000000000101100000000000010101100000000001010100000000000101001000000000010100000000000001001110000000000100110000000000010010100000000001101000000000000110011000000000011001000000000001100010000000000110000 (
b101 !
b101 $
b110101 #
b110101 %
1"
#10600000
0"
#10700000
b110 !
b110 $
b110110 #
b110110 %
b101111000000000010111000000000001011010000000000101100000000000010101100000000001010100000000000101001000000000010100000000000001001110000000000100110000000000011010100000000001101000000000000110011000000000011001000000000001100010000000000110000 &
b101111000000000010111000000000001011010000000000101100000000000010101100000000001010100000000000101001000000000010100000000000001001110000000000100110000000000011010100000000001101000000000000110011000000000011001000000000001100010000000000110000 (
1"
#10800000
0"
#10900000
b101111000000000010111000000000001011010000000000101100000000000010101100000000001010100000000000101001000000000010100000000000001001110000000000110110000000000011010100000000001101000000000000110011000000000011001000000000001100010000000000110000 &
b101111000000000010111000000000001011010000000000101100000000000010101100000000001010100000000000101001000000000010100000000000001001110000000000110110000000000011010100000000001101000000000000110011000000000011001000000000001100010000000000110000 (
b111 !
b111 $
b110111 #
b110111 %
1"
#11000000
0"
#11100000
b1000 !
b1000 $
b111000 #
b111000 %
b101111000000000010111000000000001011010000000000101100000000000010101100000000001010100000000000101001000000000010100000000000001101110000000000110110000000000011010100000000001101000000000000110011000000000011001000000000001100010000000000110000 &
b101111000000000010111000000000001011010000000000101100000000000010101100000000001010100000000000101001000000000010100000000000001101110000000000110110000000000011010100000000001101000000000000110011000000000011001000000000001100010000000000110000 (
1"
#11200000
0"
#11300000
b101111000000000010111000000000001011010000000000101100000000000010101100000000001010100000000000101001000000000011100000000000001101110000000000110110000000000011010100000000001101000000000000110011000000000011001000000000001100010000000000110000 &
b101111000000000010111000000000001011010000000000101100000000000010101100000000001010100000000000101001000000000011100000000000001101110000000000110110000000000011010100000000001101000000000000110011000000000011001000000000001100010000000000110000 (
b1001 !
b1001 $
b111001 #
b111001 %
1"
#11400000
0"
#11500000
b1010 !
b1010 $
b111010 #
b111010 %
b101111000000000010111000000000001011010000000000101100000000000010101100000000001010100000000000111001000000000011100000000000001101110000000000110110000000000011010100000000001101000000000000110011000000000011001000000000001100010000000000110000 &
b101111000000000010111000000000001011010000000000101100000000000010101100000000001010100000000000111001000000000011100000000000001101110000000000110110000000000011010100000000001101000000000000110011000000000011001000000000001100010000000000110000 (
1"
#11600000
0"
#11700000
b101111000000000010111000000000001011010000000000101100000000000010101100000000001110100000000000111001000000000011100000000000001101110000000000110110000000000011010100000000001101000000000000110011000000000011001000000000001100010000000000110000 &
b101111000000000010111000000000001011010000000000101100000000000010101100000000001110100000000000111001000000000011100000000000001101110000000000110110000000000011010100000000001101000000000000110011000000000011001000000000001100010000000000110000 (
b1011 !
b1011 $
b111011 #
b111011 %
1"
#11800000
0"
#11900000
b1100 !
b1100 $
b111100 #
b111100 %
b101111000000000010111000000000001011010000000000101100000000000011101100000000001110100000000000111001000000000011100000000000001101110000000000110110000000000011010100000000001101000000000000110011000000000011001000000000001100010000000000110000 &
b101111000000000010111000000000001011010000000000101100000000000011101100000000001110100000000000111001000000000011100000000000001101110000000000110110000000000011010100000000001101000000000000110011000000000011001000000000001100010000000000110000 (
1"
#12000000
0"
#12100000
b101111000000000010111000000000001011010000000000111100000000000011101100000000001110100000000000111001000000000011100000000000001101110000000000110110000000000011010100000000001101000000000000110011000000000011001000000000001100010000000000110000 &
b101111000000000010111000000000001011010000000000111100000000000011101100000000001110100000000000111001000000000011100000000000001101110000000000110110000000000011010100000000001101000000000000110011000000000011001000000000001100010000000000110000 (
b1101 !
b1101 $
b111101 #
b111101 %
1"
#12200000
0"
#12300000
b1110 !
b1110 $
b111110 #
b111110 %
b101111000000000010111000000000001111010000000000111100000000000011101100000000001110100000000000111001000000000011100000000000001101110000000000110110000000000011010100000000001101000000000000110011000000000011001000000000001100010000000000110000 &
b101111000000000010111000000000001111010000000000111100000000000011101100000000001110100000000000111001000000000011100000000000001101110000000000110110000000000011010100000000001101000000000000110011000000000011001000000000001100010000000000110000 (
1"
#12400000
0"
#12500000
b101111000000000011111000000000001111010000000000111100000000000011101100000000001110100000000000111001000000000011100000000000001101110000000000110110000000000011010100000000001101000000000000110011000000000011001000000000001100010000000000110000 &
b101111000000000011111000000000001111010000000000111100000000000011101100000000001110100000000000111001000000000011100000000000001101110000000000110110000000000011010100000000001101000000000000110011000000000011001000000000001100010000000000110000 (
b1111 !
b1111 $
b111111 #
b111111 %
1"
#12600000
0"
#12700000
b0 !
b0 $
b1000000 #
b1000000 %
b111111000000000011111000000000001111010000000000111100000000000011101100000000001110100000000000111001000000000011100000000000001101110000000000110110000000000011010100000000001101000000000000110011000000000011001000000000001100010000000000110000 &
b111111000000000011111000000000001111010000000000111100000000000011101100000000001110100000000000111001000000000011100000000000001101110000000000110110000000000011010100000000001101000000000000110011000000000011001000000000001100010000000000110000 (
1"
#12800000
0"
#12900000
b111111000000000011111000000000001111010000000000111100000000000011101100000000001110100000000000111001000000000011100000000000001101110000000000110110000000000011010100000000001101000000000000110011000000000011001000000000001100010000000001000000 &
b111111000000000011111000000000001111010000000000111100000000000011101100000000001110100000000000111001000000000011100000000000001101110000000000110110000000000011010100000000001101000000000000110011000000000011001000000000001100010000000001000000 (
b1 !
b1 $
b1000001 #
b1000001 %
1"
#13000000
0"
#13100000
b10 !
b10 $
b1000010 #
b1000010 %
b111111000000000011111000000000001111010000000000111100000000000011101100000000001110100000000000111001000000000011100000000000001101110000000000110110000000000011010100000000001101000000000000110011000000000011001000000000010000010000000001000000 &
b111111000000000011111000000000001111010000000000111100000000000011101100000000001110100000000000111001000000000011100000000000001101110000000000110110000000000011010100000000001101000000000000110011000000000011001000000000010000010000000001000000 (
1"
#13200000
0"
#13300000
b111111000000000011111000000000001111010000000000111100000000000011101100000000001110100000000000111001000000000011100000000000001101110000000000110110000000000011010100000000001101000000000000110011000000000100001000000000010000010000000001000000 &
b111111000000000011111000000000001111010000000000111100000000000011101100000000001110100000000000111001000000000011100000000000001101110000000000110110000000000011010100000000001101000000000000110011000000000100001000000000010000010000000001000000 (
b11 !
b11 $
b1000011 #
b1000011 %
1"
#13400000
0"
#13500000
b100 !
b100 $
b1000100 #
b1000100 %
b111111000000000011111000000000001111010000000000111100000000000011101100000000001110100000000000111001000000000011100000000000001101110000000000110110000000000011010100000000001101000000000001000011000000000100001000000000010000010000000001000000 &
b111111000000000011111000000000001111010000000000111100000000000011101100000000001110100000000000111001000000000011100000000000001101110000000000110110000000000011010100000000001101000000000001000011000000000100001000000000010000010000000001000000 (
1"
#13600000
0"
#13700000
b111111000000000011111000000000001111010000000000111100000000000011101100000000001110100000000000111001000000000011100000000000001101110000000000110110000000000011010100000000010001000000000001000011000000000100001000000000010000010000000001000000 &
b111111000000000011111000000000001111010000000000111100000000000011101100000000001110100000000000111001000000000011100000000000001101110000000000110110000000000011010100000000010001000000000001000011000000000100001000000000010000010000000001000000 (
b101 !
b101 $
b1000101 #
b1000101 %
1"
#13800000
0"
#13900000
b110 !
b110 $
b1000110 #
b1000110 %
b111111000000000011111000000000001111010000000000111100000000000011101100000000001110100000000000111001000000000011100000000000001101110000000000110110000000000100010100000000010001000000000001000011000000000100001000000000010000010000000001000000 &
b111111000000000011111000000000001111010000000000111100000000000011101100000000001110100000000000111001000000000011100000000000001101110000000000110110000000000100010100000000010001000000000001000011000000000100001000000000010000010000000001000000 (
1"
#14000000
0"
#14100000
b111111000000000011111000000000001111010000000000111100000000000011101100000000001110100000000000111001000000000011100000000000001101110000000001000110000000000100010100000000010001000000000001000011000000000100001000000000010000010000000001000000 &
b111111000000000011111000000000001111010000000000111100000000000011101100000000001110100000000000111001000000000011100000000000001101110000000001000110000000000100010100000000010001000000000001000011000000000100001000000000010000010000000001000000 (
b111 !
b111 $
b1000111 #
b1000111 %
1"
#14200000
0"
#14300000
b1000 !
b1000 $
b1001000 #
b1001000 %
b111111000000000011111000000000001111010000000000111100000000000011101100000000001110100000000000111001000000000011100000000000010001110000000001000110000000000100010100000000010001000000000001000011000000000100001000000000010000010000000001000000 &
b111111000000000011111000000000001111010000000000111100000000000011101100000000001110100000000000111001000000000011100000000000010001110000000001000110000000000100010100000000010001000000000001000011000000000100001000000000010000010000000001000000 (
1"
#14400000
0"
#14500000
b111111000000000011111000000000001111010000000000111100000000000011101100000000001110100000000000111001000000000100100000000000010001110000000001000110000000000100010100000000010001000000000001000011000000000100001000000000010000010000000001000000 &
b111111000000000011111000000000001111010000000000111100000000000011101100000000001110100000000000111001000000000100100000000000010001110000000001000110000000000100010100000000010001000000000001000011000000000100001000000000010000010000000001000000 (
b1001 !
b1001 $
b1001001 #
b1001001 %
1"
#14600000
0"
