FFT_stage/clean/index_mapper.v
module index_mapper #(parameter MSB = 8)
	(
		input [MSB-1:0] index_in,
		input [$clog2(MSB)-1:0] stage,
		output [MSB-1:0]  index_out
		);

integer i;
reg [MSB-1:0] tmp;
reg [MSB/2-1:0]stage_plus; 

always @(*)
begin
	stage_plus <= stage +1'b1;
	if (stage <= MSB/2)
	begin
		for(i=0;i<MSB;i=i+1)
		begin
			if(i>=MSB-stage_plus)
			begin
				tmp[i] <= index_in[MSB-1-stage_plus+(MSB-i)];
			end
			else if(i<MSB-stage_plus)
			begin
				tmp[i] <= index_in[i];
			end
		end
	end
	else
		begin
			tmp[MSB-1:1] <= index_in[MSB-1:1];
			tmp[0] <= index_in[MSB-1];
			tmp[MSB-1] <= index_in[0];
		end
end
assign index_out = tmp;
endmodule // index_mapper

FFT_stage/sim/idxsim/idx_tb.v
`define DUMPSTR(x) `"x.vcd`"
`timescale 100 ns / 10 ns

module tb_idx;

parameter DURATION = 1000;

reg [7:0] count;

reg clk;
reg [1:0] stage = 0;

reg [$clog2(8)-1:0]addr  = 0;


reg start = 1'b0;

index_mapper #(.MSB(3)) idx_map
(
	.index_in(addr),
	.stage(stage)
	);

always #1 clk <= ~clk;



initial begin
	clk <= 0;
	count <= 0;


$dumpfile(`DUMPSTR(`VCD_OUTPUT));
  $dumpvars(0, tb_idx);

   #(DURATION) $display("End of simulation");
  $finish;

end

always @ (posedge clk)
	begin
		addr = addr + 1'b1;
		if(addr == 0)stage = stage + 1'b1;
	end

endmodule // tb_adder

FFT_stage/sim/idxsim/idx_tb.vcd
$date
	Sat Jul 30 18:52:51 2022
$end
$version
	Icarus Verilog
$end
$timescale
	1ps
$end
$scope module tb_idx $end
$var reg 3 ! addr [2:0] $end
$var reg 1 " clk $end
$var reg 8 # count [7:0] $end
$var reg 2 $ stage [1:0] $end
$var reg 1 % start $end
$scope module idx_map $end
$var wire 3 & index_in [2:0] $end
$var wire 3 ' index_out [2:0] $end
$var wire 2 ( stage [1:0] $end
$var reg 2 ) stage_plus [1:0] $end
$var reg 3 * tmp [2:0] $end
$var integer 32 + i [31:0] $end
$upscope $end
$upscope $end
$enddefinitions $end
#0
$dumpvars
b11 +
b0 *
b1 )
b0 (
b0 '
b0 &
0%
b0 $
b0 #
0"
b0 !
$end
#100000
b1 '
b1 *
b11 +
b1 !
b1 &
1"
#200000
0"
#300000
b10 '
b10 *
b11 +
b10 !
b10 &
1"
#400000
0"
#500000
b11 '
b11 *
b11 +
b11 !
b11 &
1"
#600000
0"
#700000
b100 '
b100 *
b11 +
b100 !
b100 &
1"
#800000
0"
#900000
b101 '
b101 *
b11 +
b101 !
b101 &
1"
#1000000
0"
#1100000
b110 '
b110 *
b11 +
b110 !
b110 &
1"
#1200000
0"
#1300000
b111 '
b111 *
b11 +
b111 !
b111 &
1"
#1400000
0"
#1500000
b0 '
b0 *
b10 )
b11 +
b1 $
b1 (
b0 !
b0 &
1"
#1600000
0"
#1700000
b1 '
b1 *
b11 +
b1 !
b1 &
1"
#1800000
0"
#1900000
b100 '
b100 *
b11 +
b10 !
b10 &
1"
#2000000
0"
#2100000
b101 '
b101 *
b11 +
b11 !
b11 &
1"
#2200000
0"
#2300000
b10 '
b10 *
b11 +
b100 !
b100 &
1"
#2400000
0"
#2500000
b11 '
b11 *
b11 +
b101 !
b101 &
1"
#2600000
0"
#2700000
b110 '
b110 *
b11 +
b110 !
b110 &
1"
#2800000
0"
#2900000
b111 '
b111 *
b11 +
b111 !
b111 &
1"
#3000000
0"
#3100000
b0 '
b0 *
b11 )
b10 $
b10 (
b0 !
b0 &
1"
#3200000
0"
#3300000
b100 '
b100 *
b1 !
b1 &
1"
#3400000
0"
#3500000
b10 '
b10 *
b10 !
b10 &
1"
#3600000
0"
#3700000
b110 '
b110 *
b11 !
b11 &
1"
#3800000
0"
#3900000
b1 '
b1 *
b100 !
b100 &
1"
#4000000
0"
#4100000
b101 '
b101 *
b101 !
b101 &
1"
#4200000
0"
#4300000
b11 '
b11 *
b110 !
b110 &
1"
#4400000
0"
#4500000
b111 '
b111 *
b111 !
b111 &
1"
#4600000
0"
#4700000
b0 '
b0 *
b0 )
b11 $
b11 (
b0 !
b0 &
1"
#4800000
0"
#4900000
b100 '
b100 *
b1 !
b1 &
1"
#5000000
0"
#5100000
b10 '
b10 *
b10 !
b10 &
1"
#5200000
0"
#5300000
b110 '
b110 *
b11 !
b11 &
1"
#5400000
0"
#5500000
b1 '
b1 *
b100 !
b100 &
1"
#5600000
0"
#5700000
b101 '
b101 *
b101 !
b101 &
1"
#5800000
0"
#5900000
b11 '
b11 *
b110 !
b110 &
1"
#6000000
0"
#6100000
b111 '
b111 *
b111 !
b111 &
1"
#6200000
0"
#6300000
b0 '
b0 *
b1 )
b11 +
b0 $
b0 (
b0 !
b0 &
1"
#6400000
0"
#6500000
b1 '
b1 *
b11 +
b1 !
b1 &
1"
#6600000
0"
#6700000
b10 '
b10 *
b11 +
b10 !
b10 &
1"
#6800000
0"
#6900000
b11 '
b11 *
b11 +
b11 !
b11 &
1"
#7000000
0"
#7100000
b100 '
b100 *
b11 +
b100 !
b100 &
1"
#7200000
0"
#7300000
b101 '
b101 *
b11 +
b101 !
b101 &
1"
#7400000
0"
#7500000
b110 '
b110 *
b11 +
b110 !
b110 &
1"
#7600000
0"
#7700000
b111 '
b111 *
b11 +
b111 !
b111 &
1"
#7800000
0"
#7900000
b0 '
b0 *
b10 )
b11 +
b1 $
b1 (
b0 !
b0 &
1"
#8000000
0"
#8100000
b1 '
b1 *
b11 +
b1 !
b1 &
1"
#8200000
0"
#8300000
b100 '
b100 *
b11 +
b10 !
b10 &
1"
#8400000
0"
#8500000
b101 '
b101 *
b11 +
b11 !
b11 &
1"
#8600000
0"
#8700000
b10 '
b10 *
b11 +
b100 !
b100 &
1"
#8800000
0"
#8900000
b11 '
b11 *
b11 +
b101 !
b101 &
1"
#9000000
0"
#9100000
b110 '
b110 *
b11 +
b110 !
b110 &
1"
#9200000
0"
#9300000
b111 '
b111 *
b11 +
b111 !
b111 &
1"
#9400000
0"
#9500000
b0 '
b0 *
b11 )
b10 $
b10 (
b0 !
b0 &
1"
#9600000
0"
#9700000
b100 '
b100 *
b1 !
b1 &
1"
#9800000
0"
#9900000
b10 '
b10 *
b10 !
b10 &
1"
#10000000
0"
#10100000
b110 '
b110 *
b11 !
b11 &
1"
#10200000
0"
#10300000
b1 '
b1 *
b100 !
b100 &
1"
#10400000
0"
#10500000
b101 '
b101 *
b101 !
b101 &
1"
#10600000
0"
#10700000
b11 '
b11 *
b110 !
b110 &
1"
#10800000
0"
#10900000
b111 '
b111 *
b111 !
b111 &
1"
#11000000
0"
#11100000
b0 '
b0 *
b0 )
b11 $
b11 (
b0 !
b0 &
1"
#11200000
0"
#11300000
b100 '
b100 *
b1 !
b1 &
1"
#11400000
0"
#11500000
b10 '
b10 *
b10 !
b10 &
1"
#11600000
0"
#11700000
b110 '
b110 *
b11 !
b11 &
1"
#11800000
0"
#11900000
b1 '
b1 *
b100 !
b100 &
1"
#12000000
0"
#12100000
b101 '
b101 *
b101 !
b101 &
1"
#12200000
0"
#12300000
b11 '
b11 *
b110 !
b110 &
1"
#12400000
0"
#12500000
b111 '
b111 *
b111 !
b111 &
1"
#12600000
0"
#12700000
b0 '
b0 *
b1 )
b11 +
b0 $
b0 (
b0 !
b0 &
1"
#12800000
0"
#12900000
b1 '
b1 *
b11 +
b1 !
b1 &
1"
#13000000
0"
#13100000
b10 '
b10 *
b11 +
b10 !
b10 &
1"
#13200000
0"
#13300000
b11 '
b11 *
b11 +
b11 !
b11 &
1"
#13400000
0"
#13500000
b100 '
b100 *
b11 +
b100 !
b100 &
1"
#13600000
0"
#13700000
b101 '
b101 *
b11 +
b101 !
b101 &
1"
#13800000
0"
#13900000
b110 '
b110 *
b11 +
b110 !
b110 &
1"
#14000000
0"
#14100000
b111 '
b111 *
b11 +
b111 !
b111 &
1"
#14200000
0"
#14300000
b0 '
b0 *
b10 )
b11 +
b1 $
b1 (
b0 !
b0 &
1"
#14400000
0"
#14500000
b1 '
b1 *
b11 +
b1 !
b1 &
1"
#14600000
0"
#14700000
b100 '
b100 *
b11 +
b10 !
b10 &
1"
#14800000
0"
#14900000
b101 '
b101 *
b11 +
b11 !
b11 &
1"
#15000000
0"
#15100000
b10 '
b10 *
b11 +
b100 !
b100 &
1"
#15200000
0"
#15300000
b11 '
b11 *
b11 +
b101 !
b101 &
1"
#15400000
0"
#15500000
b110 '
b110 *
b11 +
b110 !
b110 &
1"
#15600000
0"
#15700000
b111 '
b111 *
b11 +
b111 !
b111 &
1"
#15800000
0"
#15900000
b0 '
b0 *
b11 )
b10 $
b10 (
b0 !
b0 &
1"
#16000000
0"
#16100000
b100 '
b100 *
b1 !
b1 &
1"
#16200000
0"
#16300000
b10 '
b10 *
b10 !
b10 &
1"
#16400000
0"
#16500000
b110 '
b110 *
b11 !
b11 &
1"
#16600000
0"
#16700000
b1 '
b1 *
b100 !
b100 &
1"
#16800000
0"
#16900000
b101 '
b101 *
b101 !
b101 &
1"
#17000000
0"
#17100000
b11 '
b11 *
b110 !
b110 &
1"
#17200000
0"
#17300000
b111 '
b111 *
b111 !
b111 &
1"
#17400000
0"
#17500000
b0 '
b0 *
b0 )
b11 $
b11 (
b0 !
b0 &
1"
#17600000
0"
#17700000
b100 '
b100 *
b1 !
b1 &
1"
#17800000
0"
#17900000
b10 '
b10 *
b10 !
b10 &
1"
#18000000
0"
#18100000
b110 '
b110 *
b11 !
b11 &
1"
#18200000
0"
#18300000
b1 '
b1 *
b100 !
b100 &
1"
#18400000
0"
#18500000
b101 '
b101 *
b101 !
b101 &
1"
#18600000
0"
#18700000
b11 '
b11 *
b110 !
b110 &
1"
#18800000
0"
#18900000
b111 '
b111 *
b111 !
b111 &
1"
#19000000
0"
#19100000
b0 '
b0 *
b1 )
b11 +
b0 $
b0 (
b0 !
b0 &
1"
#19200000
0"
#19300000
b1 '
b1 *
b11 +
b1 !
b1 &
1"
#19400000
0"
#19500000
b10 '
b10 *
b11 +
b10 !
b10 &
1"
#19600000
0"
#19700000
b11 '
b11 *
b11 +
b11 !
b11 &
1"
#19800000
0"
#19900000
b100 '
b100 *
b11 +
b100 !
b100 &
1"
#20000000
0"
#20100000
b101 '
b101 *
b11 +
b101 !
b101 &
1"
#20200000
0"
#20300000
b110 '
b110 *
b11 +
b110 !
b110 &
1"
#20400000
0"
#20500000
b111 '
b111 *
b11 +
b111 !
b111 &
1"
#20600000
0"
#20700000
b0 '
b0 *
b10 )
b11 +
b1 $
b1 (
b0 !
b0 &
1"
#20800000
0"
#20900000
b1 '
b1 *
b11 +
b1 !
b1 &
1"
#21000000
0"
#21100000
b100 '
b100 *
b11 +
b10 !
b10 &
1"
#21200000
0"
#21300000
b101 '
b101 *
b11 +
b11 !
b11 &
1"
#21400000
0"
#21500000
b10 '
b10 *
b11 +
b100 !
b100 &
1"
#21600000
0"
#21700000
b11 '
b11 *
b11 +
b101 !
b101 &
1"
#21800000
0"
#21900000
b110 '
b110 *
b11 +
b110 !
b110 &
1"
#22000000
0"
#22100000
b111 '
b111 *
b11 +
b111 !
b111 &
1"
#22200000
0"
#22300000
b0 '
b0 *
b11 )
b10 $
b10 (
b0 !
b0 &
1"
#22400000
0"
#22500000
b100 '
b100 *
b1 !
b1 &
1"
#22600000
0"
#22700000
b10 '
b10 *
b10 !
b10 &
1"
#22800000
0"
#22900000
b110 '
b110 *
b11 !
b11 &
1"
#23000000
0"
#23100000
b1 '
b1 *
b100 !
b100 &
1"
#23200000
0"
#23300000
b101 '
b101 *
b101 !
b101 &
1"
#23400000
0"
#23500000
b11 '
b11 *
b110 !
b110 &
1"
#23600000
0"
#23700000
b111 '
b111 *
b111 !
b111 &
1"
#23800000
0"
#23900000
b0 '
b0 *
b0 )
b11 $
b11 (
b0 !
b0 &
1"
#24000000
0"
#24100000
b100 '
b100 *
b1 !
b1 &
1"
#24200000
0"
#24300000
b10 '
b10 *
b10 !
b10 &
1"
#24400000
0"
#24500000
b110 '
b110 *
b11 !
b11 &
1"
#24600000
0"
#24700000
b1 '
b1 *
b100 !
b100 &
1"
#24800000
0"
#24900000
b101 '
b101 *
b101 !
b101 &
1"
#25000000
0"
#25100000
b11 '
b11 *
b110 !
b110 &
1"
#25200000
0"
#25300000
b111 '
b111 *
b111 !
b111 &
1"
#25400000
0"
#25500000
b0 '
b0 *
b1 )
b11 +
b0 $
b0 (
b0 !
b0 &
1"
#25600000
0"
#25700000
b1 '
b1 *
b11 +
b1 !
b1 &
1"
#25800000
0"
#25900000
b10 '
b10 *
b11 +
b10 !
b10 &
1"
#26000000
0"
#26100000
b11 '
b11 *
b11 +
b11 !
b11 &
1"
#26200000
0"
#26300000
b100 '
b100 *
b11 +
b100 !
b100 &
1"
#26400000
0"
#26500000
b101 '
b101 *
b11 +
b101 !
b101 &
1"
#26600000
0"
#26700000
b110 '
b110 *
b11 +
b110 !
b110 &
1"
#26800000
0"
#26900000
b111 '
b111 *
b11 +
b111 !
b111 &
1"
#27000000
0"
#27100000
b0 '
b0 *
b10 )
b11 +
b1 $
b1 (
b0 !
b0 &
1"
#27200000
0"
#27300000
b1 '
b1 *
b11 +
b1 !
b1 &
1"
#27400000
0"
#27500000
b100 '
b100 *
b11 +
b10 !
b10 &
1"
#27600000
0"
#27700000
b101 '
b101 *
b11 +
b11 !
b11 &
1"
#27800000
0"
#27900000
b10 '
b10 *
b11 +
b100 !
b100 &
1"
#28000000
0"
#28100000
b11 '
b11 *
b11 +
b101 !
b101 &
1"
#28200000
0"
#28300000
b110 '
b110 *
b11 +
b110 !
b110 &
1"
#28400000
0"
#28500000
b111 '
b111 *
b11 +
b111 !
b111 &
1"
#28600000
0"
#28700000
b0 '
b0 *
b11 )
b10 $
b10 (
b0 !
b0 &
1"
#28800000
0"
#28900000
b100 '
b100 *
b1 !
b1 &
1"
#29000000
0"
#29100000
b10 '
b10 *
b10 !
b10 &
1"
#29200000
0"
#29300000
b110 '
b110 *
b11 !
b11 &
1"
#29400000
0"
#29500000
b1 '
b1 *
b100 !
b100 &
1"
#29600000
0"
#29700000
b101 '
b101 *
b101 !
b101 &
1"
#29800000
0"
#29900000
b11 '
b11 *
b110 !
b110 &
1"
#30000000
0"
#30100000
b111 '
b111 *
b111 !
b111 &
1"
#30200000
0"
#30300000
b0 '
b0 *
b0 )
b11 $
b11 (
b0 !
b0 &
1"
#30400000
0"
#30500000
b100 '
b100 *
b1 !
b1 &
1"
#30600000
0"
#30700000
b10 '
b10 *
b10 !
b10 &
1"
#30800000
0"
#30900000
b110 '
b110 *
b11 !
b11 &
1"
#31000000
0"
#31100000
b1 '
b1 *
b100 !
b100 &
1"
#31200000
0"
#31300000
b101 '
b101 *
b101 !
b101 &
1"
#31400000
0"
#31500000
b11 '
b11 *
b110 !
b110 &
1"
#31600000
0"
#31700000
b111 '
b111 *
b111 !
b111 &
1"
#31800000
0"
#31900000
b0 '
b0 *
b1 )
b11 +
b0 $
b0 (
b0 !
b0 &
1"
#32000000
0"
#32100000
b1 '
b1 *
b11 +
b1 !
b1 &
1"
#32200000
0"
#32300000
b10 '
b10 *
b11 +
b10 !
b10 &
1"
#32400000
0"
#32500000
b11 '
b11 *
b11 +
b11 !
b11 &
1"
#32600000
0"
#32700000
b100 '
b100 *
b11 +
b100 !
b100 &
1"
#32800000
0"
#32900000
b101 '
b101 *
b11 +
b101 !
b101 &
1"
#33000000
0"
#33100000
b110 '
b110 *
b11 +
b110 !
b110 &
1"
#33200000
0"
#33300000
b111 '
b111 *
b11 +
b111 !
b111 &
1"
#33400000
0"
#33500000
b0 '
b0 *
b10 )
b11 +
b1 $
b1 (
b0 !
b0 &
1"
#33600000
0"
#33700000
b1 '
b1 *
b11 +
b1 !
b1 &
1"
#33800000
0"
#33900000
b100 '
b100 *
b11 +
b10 !
b10 &
1"
#34000000
0"
#34100000
b101 '
b101 *
b11 +
b11 !
b11 &
1"
#34200000
0"
#34300000
b10 '
b10 *
b11 +
b100 !
b100 &
1"
#34400000
0"
#34500000
b11 '
b11 *
b11 +
b101 !
b101 &
1"
#34600000
0"
#34700000
b110 '
b110 *
b11 +
b110 !
b110 &
1"
#34800000
0"
#34900000
b111 '
b111 *
b11 +
b111 !
b111 &
1"
#35000000
0"
#35100000
b0 '
b0 *
b11 )
b10 $
b10 (
b0 !
b0 &
1"
#35200000
0"
#35300000
b100 '
b100 *
b1 !
b1 &
1"
#35400000
0"
#35500000
b10 '
b10 *
b10 !
b10 &
1"
#35600000
0"
#35700000
b110 '
b110 *
b11 !
b11 &
1"
#35800000
0"
#35900000
b1 '
b1 *
b100 !
b100 &
1"
#36000000
0"
#36100000
b101 '
b101 *
b101 !
b101 &
1"
#36200000
0"
#36300000
b11 '
b11 *
b110 !
b110 &
1"
#36400000
0"
#36500000
b111 '
b111 *
b111 !
b111 &
1"
#36600000
0"
#36700000
b0 '
b0 *
b0 )
b11 $
b11 (
b0 !
b0 &
1"
#36800000
0"
#36900000
b100 '
b100 *
b1 !
b1 &
1"
#37000000
0"
#37100000
b10 '
b10 *
b10 !
b10 &
1"
#37200000
0"
#37300000
b110 '
b110 *
b11 !
b11 &
1"
#37400000
0"
#37500000
b1 '
b1 *
b100 !
b100 &
1"
#37600000
0"
#37700000
b101 '
b101 *
b101 !
b101 &
1"
#37800000
0"
#37900000
b11 '
b11 *
b110 !
b110 &
1"
#38000000
0"
#38100000
b111 '
b111 *
b111 !
b111 &
1"
#38200000
0"
#38300000
b0 '
b0 *
b1 )
b11 +
b0 $
b0 (
b0 !
b0 &
1"
#38400000
0"
#38500000
b1 '
b1 *
b11 +
b1 !
b1 &
1"
#38600000
0"
#38700000
b10 '
b10 *
b11 +
b10 !
b10 &
1"
#38800000
0"
#38900000
b11 '
b11 *
b11 +
b11 !
b11 &
1"
#39000000
0"
#39100000
b100 '
b100 *
b11 +
b100 !
b100 &
1"
#39200000
0"
#39300000
b101 '
b101 *
b11 +
b101 !
b101 &
1"
#39400000
0"
#39500000
b110 '
b110 *
b11 +
b110 !
b110 &
1"
#39600000
0"
#39700000
b111 '
b111 *
b11 +
b111 !
b111 &
1"
#39800000
0"
#39900000
b0 '
b0 *
b10 )
b11 +
b1 $
b1 (
b0 !
b0 &
1"
#40000000
0"
#40100000
b1 '
b1 *
b11 +
b1 !
b1 &
1"
#40200000
0"
#40300000
b100 '
b100 *
b11 +
b10 !
b10 &
1"
#40400000
0"
#40500000
b101 '
b101 *
b11 +
b11 !
b11 &
1"
#40600000
0"
#40700000
b10 '
b10 *
b11 +
b100 !
b100 &
1"
#40800000
0"
#40900000
b11 '
b11 *
b11 +
b101 !
b101 &
1"
#41000000
0"
#41100000
b110 '
b110 *
b11 +
b110 !
b110 &
1"
#41200000
0"
#41300000
b111 '
b111 *
b11 +
b111 !
b111 &
1"
#41400000
0"
#41500000
b0 '
b0 *
b11 )
b10 $
b10 (
b0 !
b0 &
1"
#41600000
0"
#41700000
b100 '
b100 *
b1 !
b1 &
1"
#41800000
0"
#41900000
b10 '
b10 *
b10 !
b10 &
1"
#42000000
0"
#42100000
b110 '
b110 *
b11 !
b11 &
1"
#42200000
0"
#42300000
b1 '
b1 *
b100 !
b100 &
1"
#42400000
0"
#42500000
b101 '
b101 *
b101 !
b101 &
1"
#42600000
0"
#42700000
b11 '
b11 *
b110 !
b110 &
1"
#42800000
0"
#42900000
b111 '
b111 *
b111 !
b111 &
1"
#43000000
0"
#43100000
b0 '
b0 *
b0 )
b11 $
b11 (
b0 !
b0 &
1"
#43200000
0"
#43300000
b100 '
b100 *
b1 !
b1 &
1"
#43400000
0"
#43500000
b10 '
b10 *
b10 !
b10 &
1"
#43600000
0"
#43700000
b110 '
b110 *
b11 !
b11 &
1"
#43800000
0"
#43900000
b1 '
b1 *
b100 !
b100 &
1"
#44000000
0"
#44100000
b101 '
b101 *
b101 !
b101 &
1"
#44200000
0"
#44300000
b11 '
b11 *
b110 !
b110 &
1"
#44400000
0"
#44500000
b111 '
b111 *
b111 !
b111 &
1"
#44600000
0"
#44700000
b0 '
b0 *
b1 )
b11 +
b0 $
b0 (
b0 !
b0 &
1"
#44800000
0"
#44900000
b1 '
b1 *
b11 +
b1 !
b1 &
1"
#45000000
0"
#45100000
b10 '
b10 *
b11 +
b10 !
b10 &
1"
#45200000
0"
#45300000
b11 '
b11 *
b11 +
b11 !
b11 &
1"
#45400000
0"
#45500000
b100 '
b100 *
b11 +
b100 !
b100 &
1"
#45600000
0"
#45700000
b101 '
b101 *
b11 +
b101 !
b101 &
1"
#45800000
0"
#45900000
b110 '
b110 *
b11 +
b110 !
b110 &
1"
#46000000
0"
#46100000
b111 '
b111 *
b11 +
b111 !
b111 &
1"
#46200000
0"
#46300000
b0 '
b0 *
b10 )
b11 +
b1 $
b1 (
b0 !
b0 &
1"
#46400000
0"
#46500000
b1 '
b1 *
b11 +
b1 !
b1 &
1"
#46600000
0"
#46700000
b100 '
b100 *
b11 +
b10 !
b10 &
1"
#46800000
0"
#46900000
b101 '
b101 *
b11 +
b11 !
b11 &
1"
#47000000
0"
#47100000
b10 '
b10 *
b11 +
b100 !
b100 &
1"
#47200000
0"
#47300000
b11 '
b11 *
b11 +
b101 !
b101 &
1"
#47400000
0"
#47500000
b110 '
b110 *
b11 +
b110 !
b110 &
1"
#47600000
0"
#47700000
b111 '
b111 *
b11 +
b111 !
b111 &
1"
#47800000
0"
#47900000
b0 '
b0 *
b11 )
b10 $
b10 (
b0 !
b0 &
1"
#48000000
0"
#48100000
b100 '
b100 *
b1 !
b1 &
1"
#48200000
0"
#48300000
b10 '
b10 *
b10 !
b10 &
1"
#48400000
0"
#48500000
b110 '
b110 *
b11 !
b11 &
1"
#48600000
0"
#48700000
b1 '
b1 *
b100 !
b100 &
1"
#48800000
0"
#48900000
b101 '
b101 *
b101 !
b101 &
1"
#49000000
0"
#49100000
b11 '
b11 *
b110 !
b110 &
1"
#49200000
0"
#49300000
b111 '
b111 *
b111 !
b111 &
1"
#49400000
0"
#49500000
b0 '
b0 *
b0 )
b11 $
b11 (
b0 !
b0 &
1"
#49600000
0"
#49700000
b100 '
b100 *
b1 !
b1 &
1"
#49800000
0"
#49900000
b10 '
b10 *
b10 !
b10 &
1"
#50000000
0"
#50100000
b110 '
b110 *
b11 !
b11 &
1"
#50200000
0"
#50300000
b1 '
b1 *
b100 !
b100 &
1"
#50400000
0"
#50500000
b101 '
b101 *
b101 !
b101 &
1"
#50600000
0"
#50700000
b11 '
b11 *
b110 !
b110 &
1"
#50800000
0"
#50900000
b111 '
b111 *
b111 !
b111 &
1"
#51000000
0"
#51100000
b0 '
b0 *
b1 )
b11 +
b0 $
b0 (
b0 !
b0 &
1"
#51200000
0"
#51300000
b1 '
b1 *
b11 +
b1 !
b1 &
1"
#51400000
0"
#51500000
b10 '
b10 *
b11 +
b10 !
b10 &
1"
#51600000
0"
#51700000
b11 '
b11 *
b11 +
b11 !
b11 &
1"
#51800000
0"
#51900000
b100 '
b100 *
b11 +
b100 !
b100 &
1"
#52000000
0"
#52100000
b101 '
b101 *
b11 +
b101 !
b101 &
1"
#52200000
0"
#52300000
b110 '
b110 *
b11 +
b110 !
b110 &
1"
#52400000
0"
#52500000
b111 '
b111 *
b11 +
b111 !
b111 &
1"
#52600000
0"
#52700000
b0 '
b0 *
b10 )
b11 +
b1 $
b1 (
b0 !
b0 &
1"
#52800000
0"
#52900000
b1 '
b1 *
b11 +
b1 !
b1 &
1"
#53000000
0"
#53100000
b100 '
b100 *
b11 +
b10 !
b10 &
1"
#53200000
0"
#53300000
b101 '
b101 *
b11 +
b11 !
b11 &
1"
#53400000
0"
#53500000
b10 '
b10 *
b11 +
b100 !
b100 &
1"
#53600000
0"
#53700000
b11 '
b11 *
b11 +
b101 !
b101 &
1"
#53800000
0"
#53900000
b110 '
b110 *
b11 +
b110 !
b110 &
1"
#54000000
0"
#54100000
b111 '
b111 *
b11 +
b111 !
b111 &
1"
#54200000
0"
#54300000
b0 '
b0 *
b11 )
b10 $
b10 (
b0 !
b0 &
1"
#54400000
0"
#54500000
b100 '
b100 *
b1 !
b1 &
1"
#54600000
0"
#54700000
b10 '
b10 *
b10 !
b10 &
1"
#54800000
0"
#54900000
b110 '
b110 *
b11 !
b11 &
1"
#55000000
0"
#55100000
b1 '
b1 *
b100 !
b100 &
1"
#55200000
0"
#55300000
b101 '
b101 *
b101 !
b101 &
1"
#55400000
0"
#55500000
b11 '
b11 *
b110 !
b110 &
1"
#55600000
0"
#55700000
b111 '
b111 *
b111 !
b111 &
1"
#55800000
0"
#55900000
b0 '
b0 *
b0 )
b11 $
b11 (
b0 !
b0 &
1"
#56000000
0"
#56100000
b100 '
b100 *
b1 !
b1 &
1"
#56200000
0"
#56300000
b10 '
b10 *
b10 !
b10 &
1"
#56400000
0"
#56500000
b110 '
b110 *
b11 !
b11 &
1"
#56600000
0"
#56700000
b1 '
b1 *
b100 !
b100 &
1"
#56800000
0"
#56900000
b101 '
b101 *
b101 !
b101 &
1"
#57000000
0"
#57100000
b11 '
b11 *
b110 !
b110 &
1"
#57200000
0"
#57300000
b111 '
b111 *
b111 !
b111 &
1"
#57400000
0"
#57500000
b0 '
b0 *
b1 )
b11 +
b0 $
b0 (
b0 !
b0 &
1"
#57600000
0"
#57700000
b1 '
b1 *
b11 +
b1 !
b1 &
1"
#57800000
0"
#57900000
b10 '
b10 *
b11 +
b10 !
b10 &
1"
#58000000
0"
#58100000
b11 '
b11 *
b11 +
b11 !
b11 &
1"
#58200000
0"
#58300000
b100 '
b100 *
b11 +
b100 !
b100 &
1"
#58400000
0"
#58500000
b101 '
b101 *
b11 +
b101 !
b101 &
1"
#58600000
0"
#58700000
b110 '
b110 *
b11 +
b110 !
b110 &
1"
#58800000
0"
#58900000
b111 '
b111 *
b11 +
b111 !
b111 &
1"
#59000000
0"
#59100000
b0 '
b0 *
b10 )
b11 +
b1 $
b1 (
b0 !
b0 &
1"
#59200000
0"
#59300000
b1 '
b1 *
b11 +
b1 !
b1 &
1"
#59400000
0"
#59500000
b100 '
b100 *
b11 +
b10 !
b10 &
1"
#59600000
0"
#59700000
b101 '
b101 *
b11 +
b11 !
b11 &
1"
#59800000
0"
#59900000
b10 '
b10 *
b11 +
b100 !
b100 &
1"
#60000000
0"
#60100000
b11 '
b11 *
b11 +
b101 !
b101 &
1"
#60200000
0"
#60300000
b110 '
b110 *
b11 +
b110 !
b110 &
1"
#60400000
0"
#60500000
b111 '
b111 *
b11 +
b111 !
b111 &
1"
#60600000
0"
#60700000
b0 '
b0 *
b11 )
b10 $
b10 (
b0 !
b0 &
1"
#60800000
0"
#60900000
b100 '
b100 *
b1 !
b1 &
1"
#61000000
0"
#61100000
b10 '
b10 *
b10 !
b10 &
1"
#61200000
0"
#61300000
b110 '
b110 *
b11 !
b11 &
1"
#61400000
0"
#61500000
b1 '
b1 *
b100 !
b100 &
1"
#61600000
0"
#61700000
b101 '
b101 *
b101 !
b101 &
1"
#61800000
0"
#61900000
b11 '
b11 *
b110 !
b110 &
1"
#62000000
0"
#62100000
b111 '
b111 *
b111 !
b111 &
1"
#62200000
0"
#62300000
b0 '
b0 *
b0 )
b11 $
b11 (
b0 !
b0 &
1"
#62400000
0"
#62500000
b100 '
b100 *
b1 !
b1 &
1"
#62600000
0"
#62700000
b10 '
b10 *
b10 !
b10 &
1"
#62800000
0"
#62900000
b110 '
b110 *
b11 !
b11 &
1"
#63000000
0"
#63100000
b1 '
b1 *
b100 !
b100 &
1"
#63200000
0"
#63300000
b101 '
b101 *
b101 !
b101 &
1"
#63400000
0"
#63500000
b11 '
b11 *
b110 !
b110 &
1"
#63600000
0"
#63700000
b111 '
b111 *
b111 !
b111 &
1"
#63800000
0"
#63900000
b0 '
b0 *
b1 )
b11 +
b0 $
b0 (
b0 !
b0 &
1"
#64000000
0"
#64100000
b1 '
b1 *
b11 +
b1 !
b1 &
1"
#64200000
0"
#64300000
b10 '
b10 *
b11 +
b10 !
b10 &
1"
#64400000
0"
#64500000
b11 '
b11 *
b11 +
b11 !
b11 &
1"
#64600000
0"
#64700000
b100 '
b100 *
b11 +
b100 !
b100 &
1"
#64800000
0"
#64900000
b101 '
b101 *
b11 +
b101 !
b101 &
1"
#65000000
0"
#65100000
b110 '
b110 *
b11 +
b110 !
b110 &
1"
#65200000
0"
#65300000
b111 '
b111 *
b11 +
b111 !
b111 &
1"
#65400000
0"
#65500000
b0 '
b0 *
b10 )
b11 +
b1 $
b1 (
b0 !
b0 &
1"
#65600000
0"
#65700000
b1 '
b1 *
b11 +
b1 !
b1 &
1"
#65800000
0"
#65900000
b100 '
b100 *
b11 +
b10 !
b10 &
1"
#66000000
0"
#66100000
b101 '
b101 *
b11 +
b11 !
b11 &
1"
#66200000
0"
#66300000
b10 '
b10 *
b11 +
b100 !
b100 &
1"
#66400000
0"
#66500000
b11 '
b11 *
b11 +
b101 !
b101 &
1"
#66600000
0"
#66700000
b110 '
b110 *
b11 +
b110 !
b110 &
1"
#66800000
0"
#66900000
b111 '
b111 *
b11 +
b111 !
b111 &
1"
#67000000
0"
#67100000
b0 '
b0 *
b11 )
b10 $
b10 (
b0 !
b0 &
1"
#67200000
0"
#67300000
b100 '
b100 *
b1 !
b1 &
1"
#67400000
0"
#67500000
b10 '
b10 *
b10 !
b10 &
1"
#67600000
0"
#67700000
b110 '
b110 *
b11 !
b11 &
1"
#67800000
0"
#67900000
b1 '
b1 *
b100 !
b100 &
1"
#68000000
0"
#68100000
b101 '
b101 *
b101 !
b101 &
1"
#68200000
0"
#68300000
b11 '
b11 *
b110 !
b110 &
1"
#68400000
0"
#68500000
b111 '
b111 *
b111 !
b111 &
1"
