index_mapper/index_mapper.v
module index_mapper #(parameter MSB = 8)
	(
		input [MSB-1:0] index_in,
		input [MSB/2 - 1:0] stage,
		output [MSB-1:0]  index_out
		);

integer i;
reg [MSB-1:0] tmp;
reg [MSB-1:0] in;

always @(*)
begin
	//tmp <= index_in;
	/*for(i=0;i<stage;i=i+1)
	begin
		tmp[i+MSB-stage] <= index_in[MSB-1-i];
	end*/
	for(i=0;i<MSB;i=i+1)
	begin
		if(i>=MSB-stage)
		begin
			tmp[i] <= index_in[MSB-1-stage+(MSB-i)];
		end
		else if(i<MSB-stage)
		begin
			tmp[i] <= index_in[i];
		end
	end
end
assign index_out = tmp;
endmodule // index_mapper

index_mapper/index_mapper_tb.v
`define DUMPSTR(x) `"x.vcd`"
`timescale 100 ns / 10 ns

module tb_index;

parameter DURATION = 100;

reg [3:0] index_in = 8'b11010011;
reg [1:0] stage = 2'b10;
reg [3:0] count = 0;
reg clk;

index_mapper #(.MSB(4))
 index_test
(
.index_in (count),
.stage(stage),
.index_out()
	);

always #1 clk <= ~clk;

initial begin
	clk <= 0;


$dumpfile(`DUMPSTR(`VCD_OUTPUT));
  $dumpvars(0, tb_index);

   #(DURATION) $display("End of simulation");
  $finish;
end

always @ (posedge clk)
	begin
		count <= count + 1'b1;
	end

endmodule // tb_index

index_mapper/index_mapper_tb.vcd
$date
	Fri Jul  1 15:23:13 2022
$end
$version
	Icarus Verilog
$end
$timescale
	1ps
$end
$scope module tb_index $end
$var reg 1 ! clk $end
$var reg 4 " count [3:0] $end
$var reg 4 # index_in [3:0] $end
$var reg 2 $ stage [1:0] $end
$scope module index_test $end
$var wire 4 % index_in [3:0] $end
$var wire 4 & index_out [3:0] $end
$var wire 2 ' stage [1:0] $end
$var reg 4 ( tmp [3:0] $end
$var integer 32 ) i [31:0] $end
$upscope $end
$upscope $end
$enddefinitions $end
#0
$dumpvars
b100 )
b0 (
b10 '
b0 &
b0 %
b10 $
b11 #
b0 "
0!
$end
#100000
b1 &
b1 (
b100 )
b1 "
b1 %
1!
#200000
0!
#300000
b10 &
b10 (
b100 )
b10 "
b10 %
1!
#400000
0!
#500000
b11 &
b11 (
b100 )
b11 "
b11 %
1!
#600000
0!
#700000
b1000 &
b1000 (
b100 )
b100 "
b100 %
1!
#800000
0!
#900000
b1001 &
b1001 (
b100 )
b101 "
b101 %
1!
#1000000
0!
#1100000
b1010 &
b1010 (
b100 )
b110 "
b110 %
1!
#1200000
0!
#1300000
b1011 &
b1011 (
b100 )
b111 "
b111 %
1!
#1400000
0!
#1500000
b100 &
b100 (
b100 )
b1000 "
b1000 %
1!
#1600000
0!
#1700000
b101 &
b101 (
b100 )
b1001 "
b1001 %
1!
#1800000
0!
#1900000
b110 &
b110 (
b100 )
b1010 "
b1010 %
1!
#2000000
0!
#2100000
b111 &
b111 (
b100 )
b1011 "
b1011 %
1!
#2200000
0!
#2300000
b1100 &
b1100 (
b100 )
b1100 "
b1100 %
1!
#2400000
0!
#2500000
b1101 &
b1101 (
b100 )
b1101 "
b1101 %
1!
#2600000
0!
#2700000
b1110 &
b1110 (
b100 )
b1110 "
b1110 %
1!
#2800000
0!
#2900000
b1111 &
b1111 (
b100 )
b1111 "
b1111 %
1!
#3000000
0!
#3100000
b0 &
b0 (
b100 )
b0 "
b0 %
1!
#3200000
0!
#3300000
b1 &
b1 (
b100 )
b1 "
b1 %
1!
#3400000
0!
#3500000
b10 &
b10 (
b100 )
b10 "
b10 %
1!
#3600000
0!
#3700000
b11 &
b11 (
b100 )
b11 "
b11 %
1!
#3800000
0!
#3900000
b1000 &
b1000 (
b100 )
b100 "
b100 %
1!
#4000000
0!
#4100000
b1001 &
b1001 (
b100 )
b101 "
b101 %
1!
#4200000
0!
#4300000
b1010 &
b1010 (
b100 )
b110 "
b110 %
1!
#4400000
0!
#4500000
b1011 &
b1011 (
b100 )
b111 "
b111 %
1!
#4600000
0!
#4700000
b100 &
b100 (
b100 )
b1000 "
b1000 %
1!
#4800000
0!
#4900000
b101 &
b101 (
b100 )
b1001 "
b1001 %
1!
#5000000
0!
#5100000
b110 &
b110 (
b100 )
b1010 "
b1010 %
1!
#5200000
0!
#5300000
b111 &
b111 (
b100 )
b1011 "
b1011 %
1!
#5400000
0!
#5500000
b1100 &
b1100 (
b100 )
b1100 "
b1100 %
1!
#5600000
0!
#5700000
b1101 &
b1101 (
b100 )
b1101 "
b1101 %
1!
#5800000
0!
#5900000
b1110 &
b1110 (
b100 )
b1110 "
b1110 %
1!
#6000000
0!
#6100000
b1111 &
b1111 (
b100 )
b1111 "
b1111 %
1!
#6200000
0!
#6300000
b0 &
b0 (
b100 )
b0 "
b0 %
1!
#6400000
0!
#6500000
b1 &
b1 (
b100 )
b1 "
b1 %
1!
#6600000
0!
#6700000
b10 &
b10 (
b100 )
b10 "
b10 %
1!
#6800000
0!
#6900000
b11 &
b11 (
b100 )
b11 "
b11 %
1!
#7000000
0!
#7100000
b1000 &
b1000 (
b100 )
b100 "
b100 %
1!
#7200000
0!
#7300000
b1001 &
b1001 (
b100 )
b101 "
b101 %
1!
#7400000
0!
#7500000
b1010 &
b1010 (
b100 )
b110 "
b110 %
1!
#7600000
0!
#7700000
b1011 &
b1011 (
b100 )
b111 "
b111 %
1!
#7800000
0!
#7900000
b100 &
b100 (
b100 )
b1000 "
b1000 %
1!
#8000000
0!
#8100000
b101 &
b101 (
b100 )
b1001 "
b1001 %
1!
#8200000
0!
#8300000
b110 &
b110 (
b100 )
b1010 "
b1010 %
1!
#8400000
0!
#8500000
b111 &
b111 (
b100 )
b1011 "
b1011 %
1!
#8600000
0!
#8700000
b1100 &
b1100 (
b100 )
b1100 "
b1100 %
1!
#8800000
0!
#8900000
b1101 &
b1101 (
b100 )
b1101 "
b1101 %
1!
#9000000
0!
#9100000
b1110 &
b1110 (
b100 )
b1110 "
b1110 %
1!
#9200000
0!
#9300000
b1111 &
b1111 (
b100 )
b1111 "
b1111 %
1!
#9400000
0!
#9500000
b0 &
b0 (
b100 )
b0 "
b0 %
1!
#9600000
0!
#9700000
b1 &
b1 (
b100 )
b1 "
b1 %
1!
#9800000
0!
#9900000
b10 &
b10 (
b100 )
b10 "
b10 %
1!
